{"schema":{"fields":[{"name":"index","type":"integer"},{"name":"Unnamed: 0","type":"integer"},{"name":"Jahr","type":"integer"},{"name":"Einwohner","type":"integer"},{"name":"Bundesland","type":"string"}],"primaryKey":["index"],"pandas_version":"1.4.0"},"data":[{"index":0,"Unnamed: 0":0,"Jahr":2022,"Einwohner":13369393,"Bundesland":"Bayern"},{"index":1,"Unnamed: 0":1,"Jahr":2021,"Einwohner":13176989,"Bundesland":"Bayern"},{"index":2,"Unnamed: 0":2,"Jahr":2020,"Einwohner":13140183,"Bundesland":"Bayern"},{"index":3,"Unnamed: 0":3,"Jahr":2019,"Einwohner":13124737,"Bundesland":"Bayern"},{"index":4,"Unnamed: 0":4,"Jahr":2018,"Einwohner":13076721,"Bundesland":"Bayern"},{"index":5,"Unnamed: 0":5,"Jahr":2017,"Einwohner":12997204,"Bundesland":"Bayern"},{"index":6,"Unnamed: 0":6,"Jahr":2016,"Einwohner":12930751,"Bundesland":"Bayern"},{"index":7,"Unnamed: 0":7,"Jahr":2015,"Einwohner":12843514,"Bundesland":"Bayern"},{"index":8,"Unnamed: 0":8,"Jahr":2014,"Einwohner":12691568,"Bundesland":"Bayern"},{"index":9,"Unnamed: 0":9,"Jahr":2013,"Einwohner":12604244,"Bundesland":"Bayern"},{"index":10,"Unnamed: 0":10,"Jahr":2012,"Einwohner":12519571,"Bundesland":"Bayern"},{"index":11,"Unnamed: 0":11,"Jahr":2011,"Einwohner":12443372,"Bundesland":"Bayern"},{"index":12,"Unnamed: 0":12,"Jahr":2010,"Einwohner":12538696,"Bundesland":"Bayern"},{"index":13,"Unnamed: 0":13,"Jahr":2009,"Einwohner":12510331,"Bundesland":"Bayern"},{"index":14,"Unnamed: 0":14,"Jahr":2008,"Einwohner":12519728,"Bundesland":"Bayern"},{"index":15,"Unnamed: 0":15,"Jahr":2007,"Einwohner":12520332,"Bundesland":"Bayern"},{"index":16,"Unnamed: 0":16,"Jahr":2006,"Einwohner":12492658,"Bundesland":"Bayern"},{"index":17,"Unnamed: 0":17,"Jahr":2005,"Einwohner":12468726,"Bundesland":"Bayern"},{"index":18,"Unnamed: 0":18,"Jahr":2004,"Einwohner":12443893,"Bundesland":"Bayern"},{"index":19,"Unnamed: 0":19,"Jahr":2003,"Einwohner":12423386,"Bundesland":"Bayern"},{"index":20,"Unnamed: 0":20,"Jahr":2002,"Einwohner":12387351,"Bundesland":"Bayern"},{"index":21,"Unnamed: 0":21,"Jahr":2001,"Einwohner":12329714,"Bundesland":"Bayern"},{"index":22,"Unnamed: 0":22,"Jahr":2000,"Einwohner":12230255,"Bundesland":"Bayern"},{"index":23,"Unnamed: 0":23,"Jahr":1999,"Einwohner":12154967,"Bundesland":"Bayern"},{"index":24,"Unnamed: 0":24,"Jahr":1998,"Einwohner":12086548,"Bundesland":"Bayern"},{"index":25,"Unnamed: 0":25,"Jahr":1997,"Einwohner":12066375,"Bundesland":"Bayern"},{"index":26,"Unnamed: 0":26,"Jahr":1996,"Einwohner":12043869,"Bundesland":"Bayern"},{"index":27,"Unnamed: 0":27,"Jahr":1995,"Einwohner":11993484,"Bundesland":"Bayern"},{"index":28,"Unnamed: 0":28,"Jahr":1994,"Einwohner":11921944,"Bundesland":"Bayern"},{"index":29,"Unnamed: 0":29,"Jahr":1993,"Einwohner":11863313,"Bundesland":"Bayern"},{"index":30,"Unnamed: 0":30,"Jahr":1992,"Einwohner":11770257,"Bundesland":"Bayern"},{"index":31,"Unnamed: 0":31,"Jahr":1991,"Einwohner":11595970,"Bundesland":"Bayern"},{"index":32,"Unnamed: 0":32,"Jahr":1990,"Einwohner":11448814,"Bundesland":"Bayern"},{"index":33,"Unnamed: 0":33,"Jahr":1989,"Einwohner":11220735,"Bundesland":"Bayern"},{"index":34,"Unnamed: 0":34,"Jahr":1988,"Einwohner":11049263,"Bundesland":"Bayern"},{"index":35,"Unnamed: 0":35,"Jahr":1987,"Einwohner":10949700,"Bundesland":"Bayern"},{"index":36,"Unnamed: 0":36,"Jahr":1986,"Einwohner":11026490,"Bundesland":"Bayern"},{"index":37,"Unnamed: 0":37,"Jahr":1985,"Einwohner":10973720,"Bundesland":"Bayern"},{"index":38,"Unnamed: 0":38,"Jahr":1984,"Einwohner":10957544,"Bundesland":"Bayern"},{"index":39,"Unnamed: 0":39,"Jahr":1983,"Einwohner":10969503,"Bundesland":"Bayern"},{"index":40,"Unnamed: 0":40,"Jahr":1982,"Einwohner":10966717,"Bundesland":"Bayern"},{"index":41,"Unnamed: 0":41,"Jahr":1981,"Einwohner":10959203,"Bundesland":"Bayern"},{"index":42,"Unnamed: 0":42,"Jahr":1980,"Einwohner":10928151,"Bundesland":"Bayern"},{"index":43,"Unnamed: 0":43,"Jahr":1979,"Einwohner":10870968,"Bundesland":"Bayern"},{"index":44,"Unnamed: 0":44,"Jahr":1978,"Einwohner":10831371,"Bundesland":"Bayern"},{"index":45,"Unnamed: 0":45,"Jahr":1977,"Einwohner":10819318,"Bundesland":"Bayern"},{"index":46,"Unnamed: 0":46,"Jahr":1976,"Einwohner":10804236,"Bundesland":"Bayern"},{"index":47,"Unnamed: 0":47,"Jahr":1975,"Einwohner":10810389,"Bundesland":"Bayern"},{"index":48,"Unnamed: 0":48,"Jahr":1974,"Einwohner":10849122,"Bundesland":"Bayern"},{"index":49,"Unnamed: 0":49,"Jahr":1973,"Einwohner":10852761,"Bundesland":"Bayern"},{"index":50,"Unnamed: 0":50,"Jahr":1972,"Einwohner":10778661,"Bundesland":"Bayern"},{"index":51,"Unnamed: 0":51,"Jahr":1971,"Einwohner":10690951,"Bundesland":"Bayern"},{"index":52,"Unnamed: 0":52,"Jahr":1970,"Einwohner":10561110,"Bundesland":"Bayern"},{"index":53,"Unnamed: 0":53,"Jahr":1969,"Einwohner":10568917,"Bundesland":"Bayern"},{"index":54,"Unnamed: 0":54,"Jahr":1968,"Einwohner":10405639,"Bundesland":"Bayern"},{"index":55,"Unnamed: 0":55,"Jahr":1967,"Einwohner":10280351,"Bundesland":"Bayern"},{"index":56,"Unnamed: 0":56,"Jahr":1966,"Einwohner":10216769,"Bundesland":"Bayern"},{"index":57,"Unnamed: 0":57,"Jahr":1965,"Einwohner":10100944,"Bundesland":"Bayern"},{"index":58,"Unnamed: 0":58,"Jahr":1964,"Einwohner":9976153,"Bundesland":"Bayern"},{"index":59,"Unnamed: 0":59,"Jahr":1963,"Einwohner":9846637,"Bundesland":"Bayern"},{"index":60,"Unnamed: 0":60,"Jahr":1962,"Einwohner":9731231,"Bundesland":"Bayern"},{"index":61,"Unnamed: 0":61,"Jahr":1961,"Einwohner":9593770,"Bundesland":"Bayern"},{"index":62,"Unnamed: 0":62,"Jahr":1960,"Einwohner":9494939,"Bundesland":"Bayern"},{"index":63,"Unnamed: 0":63,"Jahr":1959,"Einwohner":9370992,"Bundesland":"Bayern"},{"index":64,"Unnamed: 0":64,"Jahr":1958,"Einwohner":9278029,"Bundesland":"Bayern"},{"index":65,"Unnamed: 0":65,"Jahr":2022,"Einwohner":11280257,"Bundesland":"Baden-Württemberg"},{"index":66,"Unnamed: 0":66,"Jahr":2021,"Einwohner":11124642,"Bundesland":"Baden-Württemberg"},{"index":67,"Unnamed: 0":67,"Jahr":2020,"Einwohner":11103043,"Bundesland":"Baden-Württemberg"},{"index":68,"Unnamed: 0":68,"Jahr":2019,"Einwohner":11100394,"Bundesland":"Baden-Württemberg"},{"index":69,"Unnamed: 0":69,"Jahr":2018,"Einwohner":11069533,"Bundesland":"Baden-Württemberg"},{"index":70,"Unnamed: 0":70,"Jahr":2017,"Einwohner":11023425,"Bundesland":"Baden-Württemberg"},{"index":71,"Unnamed: 0":71,"Jahr":2016,"Einwohner":10951893,"Bundesland":"Baden-Württemberg"},{"index":72,"Unnamed: 0":72,"Jahr":2015,"Einwohner":10879618,"Bundesland":"Baden-Württemberg"},{"index":73,"Unnamed: 0":73,"Jahr":2014,"Einwohner":10716644,"Bundesland":"Baden-Württemberg"},{"index":74,"Unnamed: 0":74,"Jahr":2013,"Einwohner":10631278,"Bundesland":"Baden-Württemberg"},{"index":75,"Unnamed: 0":75,"Jahr":2012,"Einwohner":10569111,"Bundesland":"Baden-Württemberg"},{"index":76,"Unnamed: 0":76,"Jahr":2011,"Einwohner":10512441,"Bundesland":"Baden-Württemberg"},{"index":77,"Unnamed: 0":77,"Jahr":2010,"Einwohner":10753880,"Bundesland":"Baden-Württemberg"},{"index":78,"Unnamed: 0":78,"Jahr":2009,"Einwohner":10744921,"Bundesland":"Baden-Württemberg"},{"index":79,"Unnamed: 0":79,"Jahr":2008,"Einwohner":10749506,"Bundesland":"Baden-Württemberg"},{"index":80,"Unnamed: 0":80,"Jahr":2007,"Einwohner":10749755,"Bundesland":"Baden-Württemberg"},{"index":81,"Unnamed: 0":81,"Jahr":2006,"Einwohner":10738753,"Bundesland":"Baden-Württemberg"},{"index":82,"Unnamed: 0":82,"Jahr":2005,"Einwohner":10735701,"Bundesland":"Baden-Württemberg"},{"index":83,"Unnamed: 0":83,"Jahr":2004,"Einwohner":10717419,"Bundesland":"Baden-Württemberg"},{"index":84,"Unnamed: 0":84,"Jahr":2003,"Einwohner":10692556,"Bundesland":"Baden-Württemberg"},{"index":85,"Unnamed: 0":85,"Jahr":2002,"Einwohner":10661320,"Bundesland":"Baden-Württemberg"},{"index":86,"Unnamed: 0":86,"Jahr":2001,"Einwohner":10600906,"Bundesland":"Baden-Württemberg"},{"index":87,"Unnamed: 0":87,"Jahr":2000,"Einwohner":10524415,"Bundesland":"Baden-Württemberg"},{"index":88,"Unnamed: 0":88,"Jahr":1999,"Einwohner":10475932,"Bundesland":"Baden-Württemberg"},{"index":89,"Unnamed: 0":89,"Jahr":1998,"Einwohner":10426040,"Bundesland":"Baden-Württemberg"},{"index":90,"Unnamed: 0":90,"Jahr":1997,"Einwohner":10396610,"Bundesland":"Baden-Württemberg"},{"index":91,"Unnamed: 0":91,"Jahr":1996,"Einwohner":10374505,"Bundesland":"Baden-Württemberg"},{"index":92,"Unnamed: 0":92,"Jahr":1995,"Einwohner":10319367,"Bundesland":"Baden-Württemberg"},{"index":93,"Unnamed: 0":93,"Jahr":1994,"Einwohner":10272069,"Bundesland":"Baden-Württemberg"},{"index":94,"Unnamed: 0":94,"Jahr":1993,"Einwohner":10234026,"Bundesland":"Baden-Württemberg"},{"index":95,"Unnamed: 0":95,"Jahr":1992,"Einwohner":10148708,"Bundesland":"Baden-Württemberg"},{"index":96,"Unnamed: 0":96,"Jahr":1991,"Einwohner":10001840,"Bundesland":"Baden-Württemberg"},{"index":97,"Unnamed: 0":97,"Jahr":1990,"Einwohner":9821847,"Bundesland":"Baden-Württemberg"},{"index":98,"Unnamed: 0":98,"Jahr":1989,"Einwohner":9618696,"Bundesland":"Baden-Württemberg"},{"index":99,"Unnamed: 0":99,"Jahr":1988,"Einwohner":9432709,"Bundesland":"Baden-Württemberg"},{"index":100,"Unnamed: 0":100,"Jahr":1987,"Einwohner":9330488,"Bundesland":"Baden-Württemberg"},{"index":101,"Unnamed: 0":101,"Jahr":1986,"Einwohner":9326780,"Bundesland":"Baden-Württemberg"},{"index":102,"Unnamed: 0":102,"Jahr":1985,"Einwohner":9271370,"Bundesland":"Baden-Württemberg"},{"index":103,"Unnamed: 0":103,"Jahr":1984,"Einwohner":9241083,"Bundesland":"Baden-Württemberg"},{"index":104,"Unnamed: 0":104,"Jahr":1983,"Einwohner":9243301,"Bundesland":"Baden-Württemberg"},{"index":105,"Unnamed: 0":105,"Jahr":1982,"Einwohner":9270608,"Bundesland":"Baden-Württemberg"},{"index":106,"Unnamed: 0":106,"Jahr":1981,"Einwohner":9287921,"Bundesland":"Baden-Württemberg"},{"index":107,"Unnamed: 0":107,"Jahr":1980,"Einwohner":9258947,"Bundesland":"Baden-Württemberg"},{"index":108,"Unnamed: 0":108,"Jahr":1979,"Einwohner":9190052,"Bundesland":"Baden-Württemberg"},{"index":109,"Unnamed: 0":109,"Jahr":1978,"Einwohner":9137790,"Bundesland":"Baden-Württemberg"},{"index":110,"Unnamed: 0":110,"Jahr":1977,"Einwohner":9120453,"Bundesland":"Baden-Württemberg"},{"index":111,"Unnamed: 0":111,"Jahr":1976,"Einwohner":9119266,"Bundesland":"Baden-Württemberg"},{"index":112,"Unnamed: 0":112,"Jahr":1975,"Einwohner":9152748,"Bundesland":"Baden-Württemberg"},{"index":113,"Unnamed: 0":113,"Jahr":1974,"Einwohner":9226240,"Bundesland":"Baden-Württemberg"},{"index":114,"Unnamed: 0":114,"Jahr":1973,"Einwohner":9239376,"Bundesland":"Baden-Württemberg"},{"index":115,"Unnamed: 0":115,"Jahr":1972,"Einwohner":9154152,"Bundesland":"Baden-Württemberg"},{"index":116,"Unnamed: 0":116,"Jahr":1971,"Einwohner":9055114,"Bundesland":"Baden-Württemberg"},{"index":117,"Unnamed: 0":117,"Jahr":1970,"Einwohner":8953607,"Bundesland":"Baden-Württemberg"},{"index":118,"Unnamed: 0":118,"Jahr":1969,"Einwohner":8909699,"Bundesland":"Baden-Württemberg"},{"index":119,"Unnamed: 0":119,"Jahr":1968,"Einwohner":8713893,"Bundesland":"Baden-Württemberg"},{"index":120,"Unnamed: 0":120,"Jahr":1967,"Einwohner":8565471,"Bundesland":"Baden-Württemberg"},{"index":121,"Unnamed: 0":121,"Jahr":1966,"Einwohner":8534106,"Bundesland":"Baden-Württemberg"},{"index":122,"Unnamed: 0":122,"Jahr":1965,"Einwohner":8426202,"Bundesland":"Baden-Württemberg"},{"index":123,"Unnamed: 0":123,"Jahr":1964,"Einwohner":8257397,"Bundesland":"Baden-Württemberg"},{"index":124,"Unnamed: 0":124,"Jahr":1963,"Einwohner":8108335,"Bundesland":"Baden-Württemberg"},{"index":125,"Unnamed: 0":125,"Jahr":1962,"Einwohner":7990638,"Bundesland":"Baden-Württemberg"},{"index":126,"Unnamed: 0":126,"Jahr":1961,"Einwohner":7838682,"Bundesland":"Baden-Württemberg"},{"index":127,"Unnamed: 0":127,"Jahr":1960,"Einwohner":7726859,"Bundesland":"Baden-Württemberg"},{"index":128,"Unnamed: 0":128,"Jahr":1959,"Einwohner":7560698,"Bundesland":"Baden-Württemberg"},{"index":129,"Unnamed: 0":129,"Jahr":1958,"Einwohner":7433007,"Bundesland":"Baden-Württemberg"},{"index":130,"Unnamed: 0":130,"Jahr":2022,"Einwohner":3755251,"Bundesland":"Berlin"},{"index":131,"Unnamed: 0":131,"Jahr":2021,"Einwohner":3677472,"Bundesland":"Berlin"},{"index":132,"Unnamed: 0":132,"Jahr":2020,"Einwohner":3664088,"Bundesland":"Berlin"},{"index":133,"Unnamed: 0":133,"Jahr":2019,"Einwohner":3669491,"Bundesland":"Berlin"},{"index":134,"Unnamed: 0":134,"Jahr":2018,"Einwohner":3644826,"Bundesland":"Berlin"},{"index":135,"Unnamed: 0":135,"Jahr":2017,"Einwohner":3613495,"Bundesland":"Berlin"},{"index":136,"Unnamed: 0":136,"Jahr":2016,"Einwohner":3574830,"Bundesland":"Berlin"},{"index":137,"Unnamed: 0":137,"Jahr":2015,"Einwohner":3520031,"Bundesland":"Berlin"},{"index":138,"Unnamed: 0":138,"Jahr":2014,"Einwohner":3469849,"Bundesland":"Berlin"},{"index":139,"Unnamed: 0":139,"Jahr":2013,"Einwohner":3421829,"Bundesland":"Berlin"},{"index":140,"Unnamed: 0":140,"Jahr":2012,"Einwohner":3375222,"Bundesland":"Berlin"},{"index":141,"Unnamed: 0":141,"Jahr":2011,"Einwohner":3326002,"Bundesland":"Berlin"},{"index":142,"Unnamed: 0":142,"Jahr":2010,"Einwohner":3460725,"Bundesland":"Berlin"},{"index":143,"Unnamed: 0":143,"Jahr":2009,"Einwohner":3442675,"Bundesland":"Berlin"},{"index":144,"Unnamed: 0":144,"Jahr":2008,"Einwohner":3431675,"Bundesland":"Berlin"},{"index":145,"Unnamed: 0":145,"Jahr":2007,"Einwohner":3416255,"Bundesland":"Berlin"},{"index":146,"Unnamed: 0":146,"Jahr":2006,"Einwohner":3404037,"Bundesland":"Berlin"},{"index":147,"Unnamed: 0":147,"Jahr":2005,"Einwohner":3395189,"Bundesland":"Berlin"},{"index":148,"Unnamed: 0":148,"Jahr":2004,"Einwohner":3387828,"Bundesland":"Berlin"},{"index":149,"Unnamed: 0":149,"Jahr":2003,"Einwohner":3388477,"Bundesland":"Berlin"},{"index":150,"Unnamed: 0":150,"Jahr":2002,"Einwohner":3392425,"Bundesland":"Berlin"},{"index":151,"Unnamed: 0":151,"Jahr":2001,"Einwohner":3388434,"Bundesland":"Berlin"},{"index":152,"Unnamed: 0":152,"Jahr":2000,"Einwohner":3382169,"Bundesland":"Berlin"},{"index":153,"Unnamed: 0":153,"Jahr":1999,"Einwohner":3386667,"Bundesland":"Berlin"},{"index":154,"Unnamed: 0":154,"Jahr":1998,"Einwohner":3398822,"Bundesland":"Berlin"},{"index":155,"Unnamed: 0":155,"Jahr":1997,"Einwohner":3425759,"Bundesland":"Berlin"},{"index":156,"Unnamed: 0":156,"Jahr":1996,"Einwohner":3458763,"Bundesland":"Berlin"},{"index":157,"Unnamed: 0":157,"Jahr":1995,"Einwohner":3471418,"Bundesland":"Berlin"},{"index":158,"Unnamed: 0":158,"Jahr":1994,"Einwohner":3472009,"Bundesland":"Berlin"},{"index":159,"Unnamed: 0":159,"Jahr":1993,"Einwohner":3475392,"Bundesland":"Berlin"},{"index":160,"Unnamed: 0":160,"Jahr":1992,"Einwohner":3465748,"Bundesland":"Berlin"},{"index":161,"Unnamed: 0":161,"Jahr":1991,"Einwohner":3446031,"Bundesland":"Berlin"},{"index":162,"Unnamed: 0":162,"Jahr":1990,"Einwohner":3433695,"Bundesland":"Berlin"},{"index":163,"Unnamed: 0":163,"Jahr":1989,"Einwohner":2130525,"Bundesland":"Berlin"},{"index":164,"Unnamed: 0":164,"Jahr":1988,"Einwohner":2068313,"Bundesland":"Berlin"},{"index":165,"Unnamed: 0":165,"Jahr":1987,"Einwohner":2028716,"Bundesland":"Berlin"},{"index":166,"Unnamed: 0":166,"Jahr":1986,"Einwohner":1879225,"Bundesland":"Berlin"},{"index":167,"Unnamed: 0":167,"Jahr":1985,"Einwohner":1860084,"Bundesland":"Berlin"},{"index":168,"Unnamed: 0":168,"Jahr":1984,"Einwohner":1848585,"Bundesland":"Berlin"},{"index":169,"Unnamed: 0":169,"Jahr":1983,"Einwohner":1854502,"Bundesland":"Berlin"},{"index":170,"Unnamed: 0":170,"Jahr":1982,"Einwohner":1869584,"Bundesland":"Berlin"},{"index":171,"Unnamed: 0":171,"Jahr":1981,"Einwohner":1888669,"Bundesland":"Berlin"},{"index":172,"Unnamed: 0":172,"Jahr":1980,"Einwohner":1896230,"Bundesland":"Berlin"},{"index":173,"Unnamed: 0":173,"Jahr":1979,"Einwohner":1902250,"Bundesland":"Berlin"},{"index":174,"Unnamed: 0":174,"Jahr":1978,"Einwohner":1909706,"Bundesland":"Berlin"},{"index":175,"Unnamed: 0":175,"Jahr":1977,"Einwohner":1926826,"Bundesland":"Berlin"},{"index":176,"Unnamed: 0":176,"Jahr":1976,"Einwohner":1950706,"Bundesland":"Berlin"},{"index":177,"Unnamed: 0":177,"Jahr":1975,"Einwohner":1984837,"Bundesland":"Berlin"},{"index":178,"Unnamed: 0":178,"Jahr":1974,"Einwohner":2023987,"Bundesland":"Berlin"},{"index":179,"Unnamed: 0":179,"Jahr":1973,"Einwohner":2047948,"Bundesland":"Berlin"},{"index":180,"Unnamed: 0":180,"Jahr":1972,"Einwohner":2062615,"Bundesland":"Berlin"},{"index":181,"Unnamed: 0":181,"Jahr":1971,"Einwohner":2083998,"Bundesland":"Berlin"},{"index":182,"Unnamed: 0":182,"Jahr":1970,"Einwohner":2115311,"Bundesland":"Berlin"},{"index":183,"Unnamed: 0":183,"Jahr":1969,"Einwohner":2134256,"Bundesland":"Berlin"},{"index":184,"Unnamed: 0":184,"Jahr":1968,"Einwohner":2141441,"Bundesland":"Berlin"},{"index":185,"Unnamed: 0":185,"Jahr":1967,"Einwohner":2163306,"Bundesland":"Berlin"},{"index":186,"Unnamed: 0":186,"Jahr":1966,"Einwohner":2185403,"Bundesland":"Berlin"},{"index":187,"Unnamed: 0":187,"Jahr":1965,"Einwohner":2197262,"Bundesland":"Berlin"},{"index":188,"Unnamed: 0":188,"Jahr":1964,"Einwohner":2200228,"Bundesland":"Berlin"},{"index":189,"Unnamed: 0":189,"Jahr":1963,"Einwohner":2186193,"Bundesland":"Berlin"},{"index":190,"Unnamed: 0":190,"Jahr":1962,"Einwohner":2174013,"Bundesland":"Berlin"},{"index":191,"Unnamed: 0":191,"Jahr":1961,"Einwohner":2188540,"Bundesland":"Berlin"},{"index":192,"Unnamed: 0":192,"Jahr":1960,"Einwohner":2202241,"Bundesland":"Berlin"},{"index":193,"Unnamed: 0":193,"Jahr":1959,"Einwohner":2207984,"Bundesland":"Berlin"},{"index":194,"Unnamed: 0":194,"Jahr":1958,"Einwohner":2226000,"Bundesland":"Berlin"},{"index":195,"Unnamed: 0":195,"Jahr":2022,"Einwohner":684864,"Bundesland":"Bremen"},{"index":196,"Unnamed: 0":196,"Jahr":2021,"Einwohner":676463,"Bundesland":"Bremen"},{"index":197,"Unnamed: 0":197,"Jahr":2020,"Einwohner":680130,"Bundesland":"Bremen"},{"index":198,"Unnamed: 0":198,"Jahr":2019,"Einwohner":681202,"Bundesland":"Bremen"},{"index":199,"Unnamed: 0":199,"Jahr":2018,"Einwohner":682986,"Bundesland":"Bremen"},{"index":200,"Unnamed: 0":200,"Jahr":2017,"Einwohner":681032,"Bundesland":"Bremen"},{"index":201,"Unnamed: 0":201,"Jahr":2016,"Einwohner":678753,"Bundesland":"Bremen"},{"index":202,"Unnamed: 0":202,"Jahr":2015,"Einwohner":671489,"Bundesland":"Bremen"},{"index":203,"Unnamed: 0":203,"Jahr":2014,"Einwohner":661888,"Bundesland":"Bremen"},{"index":204,"Unnamed: 0":204,"Jahr":2013,"Einwohner":657391,"Bundesland":"Bremen"},{"index":205,"Unnamed: 0":205,"Jahr":2012,"Einwohner":654774,"Bundesland":"Bremen"},{"index":206,"Unnamed: 0":206,"Jahr":2011,"Einwohner":652182,"Bundesland":"Bremen"},{"index":207,"Unnamed: 0":207,"Jahr":2010,"Einwohner":660706,"Bundesland":"Bremen"},{"index":208,"Unnamed: 0":208,"Jahr":2009,"Einwohner":661716,"Bundesland":"Bremen"},{"index":209,"Unnamed: 0":209,"Jahr":2008,"Einwohner":661866,"Bundesland":"Bremen"},{"index":210,"Unnamed: 0":210,"Jahr":2007,"Einwohner":663082,"Bundesland":"Bremen"},{"index":211,"Unnamed: 0":211,"Jahr":2006,"Einwohner":663979,"Bundesland":"Bremen"},{"index":212,"Unnamed: 0":212,"Jahr":2005,"Einwohner":663467,"Bundesland":"Bremen"},{"index":213,"Unnamed: 0":213,"Jahr":2004,"Einwohner":663213,"Bundesland":"Bremen"},{"index":214,"Unnamed: 0":214,"Jahr":2003,"Einwohner":663129,"Bundesland":"Bremen"},{"index":215,"Unnamed: 0":215,"Jahr":2002,"Einwohner":662098,"Bundesland":"Bremen"},{"index":216,"Unnamed: 0":216,"Jahr":2001,"Einwohner":659651,"Bundesland":"Bremen"},{"index":217,"Unnamed: 0":217,"Jahr":2000,"Einwohner":660225,"Bundesland":"Bremen"},{"index":218,"Unnamed: 0":218,"Jahr":1999,"Einwohner":663065,"Bundesland":"Bremen"},{"index":219,"Unnamed: 0":219,"Jahr":1998,"Einwohner":667965,"Bundesland":"Bremen"},{"index":220,"Unnamed: 0":220,"Jahr":1997,"Einwohner":673883,"Bundesland":"Bremen"},{"index":221,"Unnamed: 0":221,"Jahr":1996,"Einwohner":677770,"Bundesland":"Bremen"},{"index":222,"Unnamed: 0":222,"Jahr":1995,"Einwohner":679757,"Bundesland":"Bremen"},{"index":223,"Unnamed: 0":223,"Jahr":1994,"Einwohner":680029,"Bundesland":"Bremen"},{"index":224,"Unnamed: 0":224,"Jahr":1993,"Einwohner":683096,"Bundesland":"Bremen"},{"index":225,"Unnamed: 0":225,"Jahr":1992,"Einwohner":685845,"Bundesland":"Bremen"},{"index":226,"Unnamed: 0":226,"Jahr":1991,"Einwohner":683684,"Bundesland":"Bremen"},{"index":227,"Unnamed: 0":227,"Jahr":1990,"Einwohner":681665,"Bundesland":"Bremen"},{"index":228,"Unnamed: 0":228,"Jahr":1989,"Einwohner":673684,"Bundesland":"Bremen"},{"index":229,"Unnamed: 0":229,"Jahr":1988,"Einwohner":661992,"Bundesland":"Bremen"},{"index":230,"Unnamed: 0":230,"Jahr":1987,"Einwohner":658891,"Bundesland":"Bremen"},{"index":231,"Unnamed: 0":231,"Jahr":1986,"Einwohner":654170,"Bundesland":"Bremen"},{"index":232,"Unnamed: 0":232,"Jahr":1985,"Einwohner":659898,"Bundesland":"Bremen"},{"index":233,"Unnamed: 0":233,"Jahr":1984,"Einwohner":665615,"Bundesland":"Bremen"},{"index":234,"Unnamed: 0":234,"Jahr":1983,"Einwohner":676933,"Bundesland":"Bremen"},{"index":235,"Unnamed: 0":235,"Jahr":1982,"Einwohner":685388,"Bundesland":"Bremen"},{"index":236,"Unnamed: 0":236,"Jahr":1981,"Einwohner":691366,"Bundesland":"Bremen"},{"index":237,"Unnamed: 0":237,"Jahr":1980,"Einwohner":693846,"Bundesland":"Bremen"},{"index":238,"Unnamed: 0":238,"Jahr":1979,"Einwohner":695115,"Bundesland":"Bremen"},{"index":239,"Unnamed: 0":239,"Jahr":1978,"Einwohner":698277,"Bundesland":"Bremen"},{"index":240,"Unnamed: 0":240,"Jahr":1977,"Einwohner":703169,"Bundesland":"Bremen"},{"index":241,"Unnamed: 0":241,"Jahr":1976,"Einwohner":709972,"Bundesland":"Bremen"},{"index":242,"Unnamed: 0":242,"Jahr":1975,"Einwohner":716805,"Bundesland":"Bremen"},{"index":243,"Unnamed: 0":243,"Jahr":1974,"Einwohner":723959,"Bundesland":"Bremen"},{"index":244,"Unnamed: 0":244,"Jahr":1973,"Einwohner":728843,"Bundesland":"Bremen"},{"index":245,"Unnamed: 0":245,"Jahr":1972,"Einwohner":734330,"Bundesland":"Bremen"},{"index":246,"Unnamed: 0":246,"Jahr":1971,"Einwohner":739094,"Bundesland":"Bremen"},{"index":247,"Unnamed: 0":247,"Jahr":1970,"Einwohner":735452,"Bundesland":"Bremen"},{"index":248,"Unnamed: 0":248,"Jahr":1969,"Einwohner":755977,"Bundesland":"Bremen"},{"index":249,"Unnamed: 0":249,"Jahr":1968,"Einwohner":754193,"Bundesland":"Bremen"},{"index":250,"Unnamed: 0":250,"Jahr":1967,"Einwohner":751785,"Bundesland":"Bremen"},{"index":251,"Unnamed: 0":251,"Jahr":1966,"Einwohner":749649,"Bundesland":"Bremen"},{"index":252,"Unnamed: 0":252,"Jahr":1965,"Einwohner":742461,"Bundesland":"Bremen"},{"index":253,"Unnamed: 0":253,"Jahr":1964,"Einwohner":732621,"Bundesland":"Bremen"},{"index":254,"Unnamed: 0":254,"Jahr":1963,"Einwohner":724839,"Bundesland":"Bremen"},{"index":255,"Unnamed: 0":255,"Jahr":1962,"Einwohner":718332,"Bundesland":"Bremen"},{"index":256,"Unnamed: 0":256,"Jahr":1961,"Einwohner":712151,"Bundesland":"Bremen"},{"index":257,"Unnamed: 0":257,"Jahr":1960,"Einwohner":704287,"Bundesland":"Bremen"},{"index":258,"Unnamed: 0":258,"Jahr":1959,"Einwohner":691636,"Bundesland":"Bremen"},{"index":259,"Unnamed: 0":259,"Jahr":1958,"Einwohner":677533,"Bundesland":"Bremen"},{"index":260,"Unnamed: 0":260,"Jahr":2022,"Einwohner":2573135,"Bundesland":"Brandenburg"},{"index":261,"Unnamed: 0":261,"Jahr":2021,"Einwohner":2537868,"Bundesland":"Brandenburg"},{"index":262,"Unnamed: 0":262,"Jahr":2020,"Einwohner":2531071,"Bundesland":"Brandenburg"},{"index":263,"Unnamed: 0":263,"Jahr":2019,"Einwohner":2521893,"Bundesland":"Brandenburg"},{"index":264,"Unnamed: 0":264,"Jahr":2018,"Einwohner":2511917,"Bundesland":"Brandenburg"},{"index":265,"Unnamed: 0":265,"Jahr":2017,"Einwohner":2504040,"Bundesland":"Brandenburg"},{"index":266,"Unnamed: 0":266,"Jahr":2016,"Einwohner":2494648,"Bundesland":"Brandenburg"},{"index":267,"Unnamed: 0":267,"Jahr":2015,"Einwohner":2484826,"Bundesland":"Brandenburg"},{"index":268,"Unnamed: 0":268,"Jahr":2014,"Einwohner":2457872,"Bundesland":"Brandenburg"},{"index":269,"Unnamed: 0":269,"Jahr":2013,"Einwohner":2449193,"Bundesland":"Brandenburg"},{"index":270,"Unnamed: 0":270,"Jahr":2012,"Einwohner":2449511,"Bundesland":"Brandenburg"},{"index":271,"Unnamed: 0":271,"Jahr":2011,"Einwohner":2453180,"Bundesland":"Brandenburg"},{"index":272,"Unnamed: 0":272,"Jahr":2010,"Einwohner":2503273,"Bundesland":"Brandenburg"},{"index":273,"Unnamed: 0":273,"Jahr":2009,"Einwohner":2512000,"Bundesland":"Brandenburg"},{"index":274,"Unnamed: 0":274,"Jahr":2008,"Einwohner":2522000,"Bundesland":"Brandenburg"},{"index":275,"Unnamed: 0":275,"Jahr":2007,"Einwohner":2536000,"Bundesland":"Brandenburg"},{"index":276,"Unnamed: 0":276,"Jahr":2006,"Einwohner":2548000,"Bundesland":"Brandenburg"},{"index":277,"Unnamed: 0":277,"Jahr":2005,"Einwohner":2559483,"Bundesland":"Brandenburg"},{"index":278,"Unnamed: 0":278,"Jahr":2004,"Einwohner":2568000,"Bundesland":"Brandenburg"},{"index":279,"Unnamed: 0":279,"Jahr":2003,"Einwohner":2575000,"Bundesland":"Brandenburg"},{"index":280,"Unnamed: 0":280,"Jahr":2002,"Einwohner":2582000,"Bundesland":"Brandenburg"},{"index":281,"Unnamed: 0":281,"Jahr":2001,"Einwohner":2593000,"Bundesland":"Brandenburg"},{"index":282,"Unnamed: 0":282,"Jahr":2000,"Einwohner":2601962,"Bundesland":"Brandenburg"},{"index":283,"Unnamed: 0":283,"Jahr":1999,"Einwohner":2601000,"Bundesland":"Brandenburg"},{"index":284,"Unnamed: 0":284,"Jahr":1998,"Einwohner":2590000,"Bundesland":"Brandenburg"},{"index":285,"Unnamed: 0":285,"Jahr":1997,"Einwohner":2573000,"Bundesland":"Brandenburg"},{"index":286,"Unnamed: 0":286,"Jahr":1996,"Einwohner":2554000,"Bundesland":"Brandenburg"},{"index":287,"Unnamed: 0":287,"Jahr":1995,"Einwohner":2542042,"Bundesland":"Brandenburg"},{"index":288,"Unnamed: 0":288,"Jahr":1994,"Einwohner":2537000,"Bundesland":"Brandenburg"},{"index":289,"Unnamed: 0":289,"Jahr":1993,"Einwohner":2538000,"Bundesland":"Brandenburg"},{"index":290,"Unnamed: 0":290,"Jahr":1992,"Einwohner":2543000,"Bundesland":"Brandenburg"},{"index":291,"Unnamed: 0":291,"Jahr":1991,"Einwohner":2543000,"Bundesland":"Brandenburg"},{"index":292,"Unnamed: 0":292,"Jahr":1990,"Einwohner":2578312,"Bundesland":"Brandenburg"},{"index":293,"Unnamed: 0":293,"Jahr":1985,"Einwohner":2660000,"Bundesland":"Brandenburg"},{"index":294,"Unnamed: 0":294,"Jahr":1980,"Einwohner":2660000,"Bundesland":"Brandenburg"},{"index":295,"Unnamed: 0":295,"Jahr":1970,"Einwohner":2657000,"Bundesland":"Brandenburg"},{"index":296,"Unnamed: 0":296,"Jahr":1961,"Einwohner":2625000,"Bundesland":"Brandenburg"},{"index":297,"Unnamed: 0":297,"Jahr":2022,"Einwohner":6391360,"Bundesland":"Hessen"},{"index":298,"Unnamed: 0":298,"Jahr":2021,"Einwohner":6295017,"Bundesland":"Hessen"},{"index":299,"Unnamed: 0":299,"Jahr":2020,"Einwohner":6293154,"Bundesland":"Hessen"},{"index":300,"Unnamed: 0":300,"Jahr":2019,"Einwohner":6288080,"Bundesland":"Hessen"},{"index":301,"Unnamed: 0":301,"Jahr":2018,"Einwohner":6265809,"Bundesland":"Hessen"},{"index":302,"Unnamed: 0":302,"Jahr":2017,"Einwohner":6243262,"Bundesland":"Hessen"},{"index":303,"Unnamed: 0":303,"Jahr":2016,"Einwohner":6213088,"Bundesland":"Hessen"},{"index":304,"Unnamed: 0":304,"Jahr":2015,"Einwohner":6176172,"Bundesland":"Hessen"},{"index":305,"Unnamed: 0":305,"Jahr":2014,"Einwohner":6093888,"Bundesland":"Hessen"},{"index":306,"Unnamed: 0":306,"Jahr":2013,"Einwohner":6045425,"Bundesland":"Hessen"},{"index":307,"Unnamed: 0":307,"Jahr":2012,"Einwohner":6016481,"Bundesland":"Hessen"},{"index":308,"Unnamed: 0":308,"Jahr":2011,"Einwohner":5993771,"Bundesland":"Hessen"},{"index":309,"Unnamed: 0":309,"Jahr":2010,"Einwohner":6067021,"Bundesland":"Hessen"},{"index":310,"Unnamed: 0":310,"Jahr":2009,"Einwohner":6061951,"Bundesland":"Hessen"},{"index":311,"Unnamed: 0":311,"Jahr":2008,"Einwohner":6064953,"Bundesland":"Hessen"},{"index":312,"Unnamed: 0":312,"Jahr":2007,"Einwohner":6072555,"Bundesland":"Hessen"},{"index":313,"Unnamed: 0":313,"Jahr":2006,"Einwohner":6075359,"Bundesland":"Hessen"},{"index":314,"Unnamed: 0":314,"Jahr":2005,"Einwohner":6092354,"Bundesland":"Hessen"},{"index":315,"Unnamed: 0":315,"Jahr":2004,"Einwohner":6097765,"Bundesland":"Hessen"},{"index":316,"Unnamed: 0":316,"Jahr":2003,"Einwohner":6089428,"Bundesland":"Hessen"},{"index":317,"Unnamed: 0":317,"Jahr":2002,"Einwohner":6091618,"Bundesland":"Hessen"},{"index":318,"Unnamed: 0":318,"Jahr":2001,"Einwohner":6077826,"Bundesland":"Hessen"},{"index":319,"Unnamed: 0":319,"Jahr":2000,"Einwohner":6068129,"Bundesland":"Hessen"},{"index":320,"Unnamed: 0":320,"Jahr":1999,"Einwohner":6051966,"Bundesland":"Hessen"},{"index":321,"Unnamed: 0":321,"Jahr":1998,"Einwohner":6035137,"Bundesland":"Hessen"},{"index":322,"Unnamed: 0":322,"Jahr":1997,"Einwohner":6031705,"Bundesland":"Hessen"},{"index":323,"Unnamed: 0":323,"Jahr":1996,"Einwohner":6027284,"Bundesland":"Hessen"},{"index":324,"Unnamed: 0":324,"Jahr":1995,"Einwohner":6009913,"Bundesland":"Hessen"},{"index":325,"Unnamed: 0":325,"Jahr":1994,"Einwohner":5980693,"Bundesland":"Hessen"},{"index":326,"Unnamed: 0":326,"Jahr":1993,"Einwohner":5967305,"Bundesland":"Hessen"},{"index":327,"Unnamed: 0":327,"Jahr":1992,"Einwohner":5922639,"Bundesland":"Hessen"},{"index":328,"Unnamed: 0":328,"Jahr":1991,"Einwohner":5837330,"Bundesland":"Hessen"},{"index":329,"Unnamed: 0":329,"Jahr":1990,"Einwohner":5763310,"Bundesland":"Hessen"},{"index":330,"Unnamed: 0":330,"Jahr":1989,"Einwohner":5660619,"Bundesland":"Hessen"},{"index":331,"Unnamed: 0":331,"Jahr":1988,"Einwohner":5568892,"Bundesland":"Hessen"},{"index":332,"Unnamed: 0":332,"Jahr":1987,"Einwohner":5524637,"Bundesland":"Hessen"},{"index":333,"Unnamed: 0":333,"Jahr":1986,"Einwohner":5543657,"Bundesland":"Hessen"},{"index":334,"Unnamed: 0":334,"Jahr":1985,"Einwohner":5529413,"Bundesland":"Hessen"},{"index":335,"Unnamed: 0":335,"Jahr":1984,"Einwohner":5535185,"Bundesland":"Hessen"},{"index":336,"Unnamed: 0":336,"Jahr":1983,"Einwohner":5564964,"Bundesland":"Hessen"},{"index":337,"Unnamed: 0":337,"Jahr":1982,"Einwohner":5599799,"Bundesland":"Hessen"},{"index":338,"Unnamed: 0":338,"Jahr":1981,"Einwohner":5611851,"Bundesland":"Hessen"},{"index":339,"Unnamed: 0":339,"Jahr":1980,"Einwohner":5601031,"Bundesland":"Hessen"},{"index":340,"Unnamed: 0":340,"Jahr":1979,"Einwohner":5576085,"Bundesland":"Hessen"},{"index":341,"Unnamed: 0":341,"Jahr":1978,"Einwohner":5553508,"Bundesland":"Hessen"},{"index":342,"Unnamed: 0":342,"Jahr":1977,"Einwohner":5540585,"Bundesland":"Hessen"},{"index":343,"Unnamed: 0":343,"Jahr":1976,"Einwohner":5538432,"Bundesland":"Hessen"},{"index":344,"Unnamed: 0":344,"Jahr":1975,"Einwohner":5549823,"Bundesland":"Hessen"},{"index":345,"Unnamed: 0":345,"Jahr":1974,"Einwohner":5576081,"Bundesland":"Hessen"},{"index":346,"Unnamed: 0":346,"Jahr":1973,"Einwohner":5583822,"Bundesland":"Hessen"},{"index":347,"Unnamed: 0":347,"Jahr":1972,"Einwohner":5532965,"Bundesland":"Hessen"},{"index":348,"Unnamed: 0":348,"Jahr":1971,"Einwohner":5489728,"Bundesland":"Hessen"},{"index":349,"Unnamed: 0":349,"Jahr":1970,"Einwohner":5424529,"Bundesland":"Hessen"},{"index":350,"Unnamed: 0":350,"Jahr":1969,"Einwohner":5422567,"Bundesland":"Hessen"},{"index":351,"Unnamed: 0":351,"Jahr":1968,"Einwohner":5333200,"Bundesland":"Hessen"},{"index":352,"Unnamed: 0":352,"Jahr":1967,"Einwohner":5262729,"Bundesland":"Hessen"},{"index":353,"Unnamed: 0":353,"Jahr":1966,"Einwohner":5239723,"Bundesland":"Hessen"},{"index":354,"Unnamed: 0":354,"Jahr":1965,"Einwohner":5170449,"Bundesland":"Hessen"},{"index":355,"Unnamed: 0":355,"Jahr":1964,"Einwohner":5086611,"Bundesland":"Hessen"},{"index":356,"Unnamed: 0":356,"Jahr":1963,"Einwohner":5004893,"Bundesland":"Hessen"},{"index":357,"Unnamed: 0":357,"Jahr":1962,"Einwohner":4936942,"Bundesland":"Hessen"},{"index":358,"Unnamed: 0":358,"Jahr":1961,"Einwohner":4861250,"Bundesland":"Hessen"},{"index":359,"Unnamed: 0":359,"Jahr":1960,"Einwohner":4783352,"Bundesland":"Hessen"},{"index":360,"Unnamed: 0":360,"Jahr":1959,"Einwohner":4702808,"Bundesland":"Hessen"},{"index":361,"Unnamed: 0":361,"Jahr":1958,"Einwohner":4651483,"Bundesland":"Hessen"},{"index":362,"Unnamed: 0":362,"Jahr":2022,"Einwohner":1628378,"Bundesland":"Mecklenburg-Vorpommern"},{"index":363,"Unnamed: 0":363,"Jahr":2021,"Einwohner":1611160,"Bundesland":"Mecklenburg-Vorpommern"},{"index":364,"Unnamed: 0":364,"Jahr":2020,"Einwohner":1610774,"Bundesland":"Mecklenburg-Vorpommern"},{"index":365,"Unnamed: 0":365,"Jahr":2019,"Einwohner":1608138,"Bundesland":"Mecklenburg-Vorpommern"},{"index":366,"Unnamed: 0":366,"Jahr":2018,"Einwohner":1609675,"Bundesland":"Mecklenburg-Vorpommern"},{"index":367,"Unnamed: 0":367,"Jahr":2017,"Einwohner":1611119,"Bundesland":"Mecklenburg-Vorpommern"},{"index":368,"Unnamed: 0":368,"Jahr":2016,"Einwohner":1610674,"Bundesland":"Mecklenburg-Vorpommern"},{"index":369,"Unnamed: 0":369,"Jahr":2015,"Einwohner":1612362,"Bundesland":"Mecklenburg-Vorpommern"},{"index":370,"Unnamed: 0":370,"Jahr":2014,"Einwohner":1599138,"Bundesland":"Mecklenburg-Vorpommern"},{"index":371,"Unnamed: 0":371,"Jahr":2013,"Einwohner":1596505,"Bundesland":"Mecklenburg-Vorpommern"},{"index":372,"Unnamed: 0":372,"Jahr":2012,"Einwohner":1600327,"Bundesland":"Mecklenburg-Vorpommern"},{"index":373,"Unnamed: 0":373,"Jahr":2011,"Einwohner":1606899,"Bundesland":"Mecklenburg-Vorpommern"},{"index":374,"Unnamed: 0":374,"Jahr":2010,"Einwohner":1642327,"Bundesland":"Mecklenburg-Vorpommern"},{"index":375,"Unnamed: 0":375,"Jahr":2009,"Einwohner":1651000,"Bundesland":"Mecklenburg-Vorpommern"},{"index":376,"Unnamed: 0":376,"Jahr":2008,"Einwohner":1664000,"Bundesland":"Mecklenburg-Vorpommern"},{"index":377,"Unnamed: 0":377,"Jahr":2007,"Einwohner":1680000,"Bundesland":"Mecklenburg-Vorpommern"},{"index":378,"Unnamed: 0":378,"Jahr":2006,"Einwohner":1694000,"Bundesland":"Mecklenburg-Vorpommern"},{"index":379,"Unnamed: 0":379,"Jahr":2005,"Einwohner":1707266,"Bundesland":"Mecklenburg-Vorpommern"},{"index":380,"Unnamed: 0":380,"Jahr":2004,"Einwohner":1720000,"Bundesland":"Mecklenburg-Vorpommern"},{"index":381,"Unnamed: 0":381,"Jahr":2003,"Einwohner":1732000,"Bundesland":"Mecklenburg-Vorpommern"},{"index":382,"Unnamed: 0":382,"Jahr":2002,"Einwohner":1745000,"Bundesland":"Mecklenburg-Vorpommern"},{"index":383,"Unnamed: 0":383,"Jahr":2001,"Einwohner":1760000,"Bundesland":"Mecklenburg-Vorpommern"},{"index":384,"Unnamed: 0":384,"Jahr":2000,"Einwohner":1775703,"Bundesland":"Mecklenburg-Vorpommern"},{"index":385,"Unnamed: 0":385,"Jahr":1999,"Einwohner":1789000,"Bundesland":"Mecklenburg-Vorpommern"},{"index":386,"Unnamed: 0":386,"Jahr":1998,"Einwohner":1799000,"Bundesland":"Mecklenburg-Vorpommern"},{"index":387,"Unnamed: 0":387,"Jahr":1997,"Einwohner":1808000,"Bundesland":"Mecklenburg-Vorpommern"},{"index":388,"Unnamed: 0":388,"Jahr":1996,"Einwohner":1817000,"Bundesland":"Mecklenburg-Vorpommern"},{"index":389,"Unnamed: 0":389,"Jahr":1995,"Einwohner":1823084,"Bundesland":"Mecklenburg-Vorpommern"},{"index":390,"Unnamed: 0":390,"Jahr":1994,"Einwohner":1832000,"Bundesland":"Mecklenburg-Vorpommern"},{"index":391,"Unnamed: 0":391,"Jahr":1993,"Einwohner":1843000,"Bundesland":"Mecklenburg-Vorpommern"},{"index":392,"Unnamed: 0":392,"Jahr":1992,"Einwohner":1865000,"Bundesland":"Mecklenburg-Vorpommern"},{"index":393,"Unnamed: 0":393,"Jahr":1991,"Einwohner":1892000,"Bundesland":"Mecklenburg-Vorpommern"},{"index":394,"Unnamed: 0":394,"Jahr":1990,"Einwohner":1923959,"Bundesland":"Mecklenburg-Vorpommern"},{"index":395,"Unnamed: 0":395,"Jahr":1985,"Einwohner":1959000,"Bundesland":"Mecklenburg-Vorpommern"},{"index":396,"Unnamed: 0":396,"Jahr":1980,"Einwohner":1944000,"Bundesland":"Mecklenburg-Vorpommern"},{"index":397,"Unnamed: 0":397,"Jahr":1970,"Einwohner":1928000,"Bundesland":"Mecklenburg-Vorpommern"},{"index":398,"Unnamed: 0":398,"Jahr":1961,"Einwohner":1923000,"Bundesland":"Mecklenburg-Vorpommern"},{"index":399,"Unnamed: 0":399,"Jahr":2022,"Einwohner":8140242,"Bundesland":"Niedersachsen"},{"index":400,"Unnamed: 0":400,"Jahr":2021,"Einwohner":8027031,"Bundesland":"Niedersachsen"},{"index":401,"Unnamed: 0":401,"Jahr":2020,"Einwohner":8003421,"Bundesland":"Niedersachsen"},{"index":402,"Unnamed: 0":402,"Jahr":2019,"Einwohner":7993608,"Bundesland":"Niedersachsen"},{"index":403,"Unnamed: 0":403,"Jahr":2018,"Einwohner":7982448,"Bundesland":"Niedersachsen"},{"index":404,"Unnamed: 0":404,"Jahr":2017,"Einwohner":7962775,"Bundesland":"Niedersachsen"},{"index":405,"Unnamed: 0":405,"Jahr":2016,"Einwohner":7945685,"Bundesland":"Niedersachsen"},{"index":406,"Unnamed: 0":406,"Jahr":2015,"Einwohner":7926599,"Bundesland":"Niedersachsen"},{"index":407,"Unnamed: 0":407,"Jahr":2014,"Einwohner":7826739,"Bundesland":"Niedersachsen"},{"index":408,"Unnamed: 0":408,"Jahr":2013,"Einwohner":7790559,"Bundesland":"Niedersachsen"},{"index":409,"Unnamed: 0":409,"Jahr":2012,"Einwohner":7778995,"Bundesland":"Niedersachsen"},{"index":410,"Unnamed: 0":410,"Jahr":2011,"Einwohner":7774253,"Bundesland":"Niedersachsen"},{"index":411,"Unnamed: 0":411,"Jahr":2010,"Einwohner":7918293,"Bundesland":"Niedersachsen"},{"index":412,"Unnamed: 0":412,"Jahr":2009,"Einwohner":7928815,"Bundesland":"Niedersachsen"},{"index":413,"Unnamed: 0":413,"Jahr":2008,"Einwohner":7947244,"Bundesland":"Niedersachsen"},{"index":414,"Unnamed: 0":414,"Jahr":2007,"Einwohner":7971684,"Bundesland":"Niedersachsen"},{"index":415,"Unnamed: 0":415,"Jahr":2006,"Einwohner":7982685,"Bundesland":"Niedersachsen"},{"index":416,"Unnamed: 0":416,"Jahr":2005,"Einwohner":7993946,"Bundesland":"Niedersachsen"},{"index":417,"Unnamed: 0":417,"Jahr":2004,"Einwohner":8000909,"Bundesland":"Niedersachsen"},{"index":418,"Unnamed: 0":418,"Jahr":2003,"Einwohner":7993415,"Bundesland":"Niedersachsen"},{"index":419,"Unnamed: 0":419,"Jahr":2002,"Einwohner":7980472,"Bundesland":"Niedersachsen"},{"index":420,"Unnamed: 0":420,"Jahr":2001,"Einwohner":7956416,"Bundesland":"Niedersachsen"},{"index":421,"Unnamed: 0":421,"Jahr":2000,"Einwohner":7926193,"Bundesland":"Niedersachsen"},{"index":422,"Unnamed: 0":422,"Jahr":1999,"Einwohner":7898760,"Bundesland":"Niedersachsen"},{"index":423,"Unnamed: 0":423,"Jahr":1998,"Einwohner":7865840,"Bundesland":"Niedersachsen"},{"index":424,"Unnamed: 0":424,"Jahr":1997,"Einwohner":7845398,"Bundesland":"Niedersachsen"},{"index":425,"Unnamed: 0":425,"Jahr":1996,"Einwohner":7815148,"Bundesland":"Niedersachsen"},{"index":426,"Unnamed: 0":426,"Jahr":1995,"Einwohner":7780422,"Bundesland":"Niedersachsen"},{"index":427,"Unnamed: 0":427,"Jahr":1994,"Einwohner":7715363,"Bundesland":"Niedersachsen"},{"index":428,"Unnamed: 0":428,"Jahr":1993,"Einwohner":7648004,"Bundesland":"Niedersachsen"},{"index":429,"Unnamed: 0":429,"Jahr":1992,"Einwohner":7577520,"Bundesland":"Niedersachsen"},{"index":430,"Unnamed: 0":430,"Jahr":1991,"Einwohner":7475790,"Bundesland":"Niedersachsen"},{"index":431,"Unnamed: 0":431,"Jahr":1990,"Einwohner":7366072,"Bundesland":"Niedersachsen"},{"index":432,"Unnamed: 0":432,"Jahr":1989,"Einwohner":7283795,"Bundesland":"Niedersachsen"},{"index":433,"Unnamed: 0":433,"Jahr":1988,"Einwohner":7184943,"Bundesland":"Niedersachsen"},{"index":434,"Unnamed: 0":434,"Jahr":1987,"Einwohner":7163602,"Bundesland":"Niedersachsen"},{"index":435,"Unnamed: 0":435,"Jahr":1986,"Einwohner":7196127,"Bundesland":"Niedersachsen"},{"index":436,"Unnamed: 0":436,"Jahr":1985,"Einwohner":7196918,"Bundesland":"Niedersachsen"},{"index":437,"Unnamed: 0":437,"Jahr":1984,"Einwohner":7216304,"Bundesland":"Niedersachsen"},{"index":438,"Unnamed: 0":438,"Jahr":1983,"Einwohner":7248536,"Bundesland":"Niedersachsen"},{"index":439,"Unnamed: 0":439,"Jahr":1982,"Einwohner":7256769,"Bundesland":"Niedersachsen"},{"index":440,"Unnamed: 0":440,"Jahr":1981,"Einwohner":7267106,"Bundesland":"Niedersachsen"},{"index":441,"Unnamed: 0":441,"Jahr":1980,"Einwohner":7256386,"Bundesland":"Niedersachsen"},{"index":442,"Unnamed: 0":442,"Jahr":1979,"Einwohner":7234000,"Bundesland":"Niedersachsen"},{"index":443,"Unnamed: 0":443,"Jahr":1978,"Einwohner":7225167,"Bundesland":"Niedersachsen"},{"index":444,"Unnamed: 0":444,"Jahr":1977,"Einwohner":7224165,"Bundesland":"Niedersachsen"},{"index":445,"Unnamed: 0":445,"Jahr":1976,"Einwohner":7226897,"Bundesland":"Niedersachsen"},{"index":446,"Unnamed: 0":446,"Jahr":1975,"Einwohner":7238502,"Bundesland":"Niedersachsen"},{"index":447,"Unnamed: 0":447,"Jahr":1974,"Einwohner":7264840,"Bundesland":"Niedersachsen"},{"index":448,"Unnamed: 0":448,"Jahr":1973,"Einwohner":7259205,"Bundesland":"Niedersachsen"},{"index":449,"Unnamed: 0":449,"Jahr":1972,"Einwohner":7214828,"Bundesland":"Niedersachsen"},{"index":450,"Unnamed: 0":450,"Jahr":1971,"Einwohner":7180500,"Bundesland":"Niedersachsen"},{"index":451,"Unnamed: 0":451,"Jahr":1970,"Einwohner":7121824,"Bundesland":"Niedersachsen"},{"index":452,"Unnamed: 0":452,"Jahr":1969,"Einwohner":7100417,"Bundesland":"Niedersachsen"},{"index":453,"Unnamed: 0":453,"Jahr":1968,"Einwohner":7039169,"Bundesland":"Niedersachsen"},{"index":454,"Unnamed: 0":454,"Jahr":1967,"Einwohner":6993194,"Bundesland":"Niedersachsen"},{"index":455,"Unnamed: 0":455,"Jahr":1966,"Einwohner":6967216,"Bundesland":"Niedersachsen"},{"index":456,"Unnamed: 0":456,"Jahr":1965,"Einwohner":6921000,"Bundesland":"Niedersachsen"},{"index":457,"Unnamed: 0":457,"Jahr":1964,"Einwohner":6854481,"Bundesland":"Niedersachsen"},{"index":458,"Unnamed: 0":458,"Jahr":1963,"Einwohner":6786416,"Bundesland":"Niedersachsen"},{"index":459,"Unnamed: 0":459,"Jahr":1962,"Einwohner":6731562,"Bundesland":"Niedersachsen"},{"index":460,"Unnamed: 0":460,"Jahr":1961,"Einwohner":6674534,"Bundesland":"Niedersachsen"},{"index":461,"Unnamed: 0":461,"Jahr":1960,"Einwohner":6576137,"Bundesland":"Niedersachsen"},{"index":462,"Unnamed: 0":462,"Jahr":1959,"Einwohner":6538416,"Bundesland":"Niedersachsen"},{"index":463,"Unnamed: 0":463,"Jahr":1958,"Einwohner":6515582,"Bundesland":"Niedersachsen"},{"index":464,"Unnamed: 0":464,"Jahr":2022,"Einwohner":18139116,"Bundesland":"Nordrhein-Westfalen"},{"index":465,"Unnamed: 0":465,"Jahr":2021,"Einwohner":17924591,"Bundesland":"Nordrhein-Westfalen"},{"index":466,"Unnamed: 0":466,"Jahr":2020,"Einwohner":17925570,"Bundesland":"Nordrhein-Westfalen"},{"index":467,"Unnamed: 0":467,"Jahr":2019,"Einwohner":17947221,"Bundesland":"Nordrhein-Westfalen"},{"index":468,"Unnamed: 0":468,"Jahr":2018,"Einwohner":17932651,"Bundesland":"Nordrhein-Westfalen"},{"index":469,"Unnamed: 0":469,"Jahr":2017,"Einwohner":17912134,"Bundesland":"Nordrhein-Westfalen"},{"index":470,"Unnamed: 0":470,"Jahr":2016,"Einwohner":17890100,"Bundesland":"Nordrhein-Westfalen"},{"index":471,"Unnamed: 0":471,"Jahr":2015,"Einwohner":17865516,"Bundesland":"Nordrhein-Westfalen"},{"index":472,"Unnamed: 0":472,"Jahr":2014,"Einwohner":17638098,"Bundesland":"Nordrhein-Westfalen"},{"index":473,"Unnamed: 0":473,"Jahr":2013,"Einwohner":17571856,"Bundesland":"Nordrhein-Westfalen"},{"index":474,"Unnamed: 0":474,"Jahr":2012,"Einwohner":17554329,"Bundesland":"Nordrhein-Westfalen"},{"index":475,"Unnamed: 0":475,"Jahr":2011,"Einwohner":17544938,"Bundesland":"Nordrhein-Westfalen"},{"index":476,"Unnamed: 0":476,"Jahr":2010,"Einwohner":17845154,"Bundesland":"Nordrhein-Westfalen"},{"index":477,"Unnamed: 0":477,"Jahr":2009,"Einwohner":17872763,"Bundesland":"Nordrhein-Westfalen"},{"index":478,"Unnamed: 0":478,"Jahr":2008,"Einwohner":17933064,"Bundesland":"Nordrhein-Westfalen"},{"index":479,"Unnamed: 0":479,"Jahr":2007,"Einwohner":17996621,"Bundesland":"Nordrhein-Westfalen"},{"index":480,"Unnamed: 0":480,"Jahr":2006,"Einwohner":18028745,"Bundesland":"Nordrhein-Westfalen"},{"index":481,"Unnamed: 0":481,"Jahr":2005,"Einwohner":18058105,"Bundesland":"Nordrhein-Westfalen"},{"index":482,"Unnamed: 0":482,"Jahr":2004,"Einwohner":18075352,"Bundesland":"Nordrhein-Westfalen"},{"index":483,"Unnamed: 0":483,"Jahr":2003,"Einwohner":18079686,"Bundesland":"Nordrhein-Westfalen"},{"index":484,"Unnamed: 0":484,"Jahr":2002,"Einwohner":18076355,"Bundesland":"Nordrhein-Westfalen"},{"index":485,"Unnamed: 0":485,"Jahr":2001,"Einwohner":18052092,"Bundesland":"Nordrhein-Westfalen"},{"index":486,"Unnamed: 0":486,"Jahr":2000,"Einwohner":18009865,"Bundesland":"Nordrhein-Westfalen"},{"index":487,"Unnamed: 0":487,"Jahr":1999,"Einwohner":17999800,"Bundesland":"Nordrhein-Westfalen"},{"index":488,"Unnamed: 0":488,"Jahr":1998,"Einwohner":17975516,"Bundesland":"Nordrhein-Westfalen"},{"index":489,"Unnamed: 0":489,"Jahr":1997,"Einwohner":17974487,"Bundesland":"Nordrhein-Westfalen"},{"index":490,"Unnamed: 0":490,"Jahr":1996,"Einwohner":17947715,"Bundesland":"Nordrhein-Westfalen"},{"index":491,"Unnamed: 0":491,"Jahr":1995,"Einwohner":17893045,"Bundesland":"Nordrhein-Westfalen"},{"index":492,"Unnamed: 0":492,"Jahr":1994,"Einwohner":17816079,"Bundesland":"Nordrhein-Westfalen"},{"index":493,"Unnamed: 0":493,"Jahr":1993,"Einwohner":17759300,"Bundesland":"Nordrhein-Westfalen"},{"index":494,"Unnamed: 0":494,"Jahr":1992,"Einwohner":17679166,"Bundesland":"Nordrhein-Westfalen"},{"index":495,"Unnamed: 0":495,"Jahr":1991,"Einwohner":17509866,"Bundesland":"Nordrhein-Westfalen"},{"index":496,"Unnamed: 0":496,"Jahr":1990,"Einwohner":17319651,"Bundesland":"Nordrhein-Westfalen"},{"index":497,"Unnamed: 0":497,"Jahr":1989,"Einwohner":17103588,"Bundesland":"Nordrhein-Westfalen"},{"index":498,"Unnamed: 0":498,"Jahr":1988,"Einwohner":16874059,"Bundesland":"Nordrhein-Westfalen"},{"index":499,"Unnamed: 0":499,"Jahr":1987,"Einwohner":16743956,"Bundesland":"Nordrhein-Westfalen"},{"index":500,"Unnamed: 0":500,"Jahr":1986,"Einwohner":16676501,"Bundesland":"Nordrhein-Westfalen"},{"index":501,"Unnamed: 0":501,"Jahr":1985,"Einwohner":16674051,"Bundesland":"Nordrhein-Westfalen"},{"index":502,"Unnamed: 0":502,"Jahr":1984,"Einwohner":16703875,"Bundesland":"Nordrhein-Westfalen"},{"index":503,"Unnamed: 0":503,"Jahr":1983,"Einwohner":16836519,"Bundesland":"Nordrhein-Westfalen"},{"index":504,"Unnamed: 0":504,"Jahr":1982,"Einwohner":16961183,"Bundesland":"Nordrhein-Westfalen"},{"index":505,"Unnamed: 0":505,"Jahr":1981,"Einwohner":17045993,"Bundesland":"Nordrhein-Westfalen"},{"index":506,"Unnamed: 0":506,"Jahr":1980,"Einwohner":17058193,"Bundesland":"Nordrhein-Westfalen"},{"index":507,"Unnamed: 0":507,"Jahr":1979,"Einwohner":17017075,"Bundesland":"Nordrhein-Westfalen"},{"index":508,"Unnamed: 0":508,"Jahr":1978,"Einwohner":17006354,"Bundesland":"Nordrhein-Westfalen"},{"index":509,"Unnamed: 0":509,"Jahr":1977,"Einwohner":17030341,"Bundesland":"Nordrhein-Westfalen"},{"index":510,"Unnamed: 0":510,"Jahr":1976,"Einwohner":17073192,"Bundesland":"Nordrhein-Westfalen"},{"index":511,"Unnamed: 0":511,"Jahr":1975,"Einwohner":17129615,"Bundesland":"Nordrhein-Westfalen"},{"index":512,"Unnamed: 0":512,"Jahr":1974,"Einwohner":17217780,"Bundesland":"Nordrhein-Westfalen"},{"index":513,"Unnamed: 0":513,"Jahr":1973,"Einwohner":17245530,"Bundesland":"Nordrhein-Westfalen"},{"index":514,"Unnamed: 0":514,"Jahr":1972,"Einwohner":17192897,"Bundesland":"Nordrhein-Westfalen"},{"index":515,"Unnamed: 0":515,"Jahr":1971,"Einwohner":17137752,"Bundesland":"Nordrhein-Westfalen"},{"index":516,"Unnamed: 0":516,"Jahr":1970,"Einwohner":17004851,"Bundesland":"Nordrhein-Westfalen"},{"index":517,"Unnamed: 0":517,"Jahr":1969,"Einwohner":17129764,"Bundesland":"Nordrhein-Westfalen"},{"index":518,"Unnamed: 0":518,"Jahr":1968,"Einwohner":16950515,"Bundesland":"Nordrhein-Westfalen"},{"index":519,"Unnamed: 0":519,"Jahr":1967,"Einwohner":16842619,"Bundesland":"Nordrhein-Westfalen"},{"index":520,"Unnamed: 0":520,"Jahr":1966,"Einwohner":16835480,"Bundesland":"Nordrhein-Westfalen"},{"index":521,"Unnamed: 0":521,"Jahr":1965,"Einwohner":16735736,"Bundesland":"Nordrhein-Westfalen"},{"index":522,"Unnamed: 0":522,"Jahr":1964,"Einwohner":16554312,"Bundesland":"Nordrhein-Westfalen"},{"index":523,"Unnamed: 0":523,"Jahr":1963,"Einwohner":16361108,"Bundesland":"Nordrhein-Westfalen"},{"index":524,"Unnamed: 0":524,"Jahr":1962,"Einwohner":16194670,"Bundesland":"Nordrhein-Westfalen"},{"index":525,"Unnamed: 0":525,"Jahr":1961,"Einwohner":16028919,"Bundesland":"Nordrhein-Westfalen"},{"index":526,"Unnamed: 0":526,"Jahr":1960,"Einwohner":15852476,"Bundesland":"Nordrhein-Westfalen"},{"index":527,"Unnamed: 0":527,"Jahr":1959,"Einwohner":15653613,"Bundesland":"Nordrhein-Westfalen"},{"index":528,"Unnamed: 0":528,"Jahr":1958,"Einwohner":15459265,"Bundesland":"Nordrhein-Westfalen"},{"index":529,"Unnamed: 0":529,"Jahr":2022,"Einwohner":4159150,"Bundesland":"Rheinland-Pfalz"},{"index":530,"Unnamed: 0":530,"Jahr":2021,"Einwohner":4106485,"Bundesland":"Rheinland-Pfalz"},{"index":531,"Unnamed: 0":531,"Jahr":2020,"Einwohner":4098391,"Bundesland":"Rheinland-Pfalz"},{"index":532,"Unnamed: 0":532,"Jahr":2019,"Einwohner":4093903,"Bundesland":"Rheinland-Pfalz"},{"index":533,"Unnamed: 0":533,"Jahr":2018,"Einwohner":4084844,"Bundesland":"Rheinland-Pfalz"},{"index":534,"Unnamed: 0":534,"Jahr":2017,"Einwohner":4073679,"Bundesland":"Rheinland-Pfalz"},{"index":535,"Unnamed: 0":535,"Jahr":2016,"Einwohner":4066053,"Bundesland":"Rheinland-Pfalz"},{"index":536,"Unnamed: 0":536,"Jahr":2015,"Einwohner":4052803,"Bundesland":"Rheinland-Pfalz"},{"index":537,"Unnamed: 0":537,"Jahr":2014,"Einwohner":4011582,"Bundesland":"Rheinland-Pfalz"},{"index":538,"Unnamed: 0":538,"Jahr":2013,"Einwohner":3994366,"Bundesland":"Rheinland-Pfalz"},{"index":539,"Unnamed: 0":539,"Jahr":2012,"Einwohner":3990278,"Bundesland":"Rheinland-Pfalz"},{"index":540,"Unnamed: 0":540,"Jahr":2011,"Einwohner":3990033,"Bundesland":"Rheinland-Pfalz"},{"index":541,"Unnamed: 0":541,"Jahr":2010,"Einwohner":4003745,"Bundesland":"Rheinland-Pfalz"},{"index":542,"Unnamed: 0":542,"Jahr":2009,"Einwohner":4012675,"Bundesland":"Rheinland-Pfalz"},{"index":543,"Unnamed: 0":543,"Jahr":2008,"Einwohner":4028351,"Bundesland":"Rheinland-Pfalz"},{"index":544,"Unnamed: 0":544,"Jahr":2007,"Einwohner":4045643,"Bundesland":"Rheinland-Pfalz"},{"index":545,"Unnamed: 0":545,"Jahr":2006,"Einwohner":4052860,"Bundesland":"Rheinland-Pfalz"},{"index":546,"Unnamed: 0":546,"Jahr":2005,"Einwohner":4058843,"Bundesland":"Rheinland-Pfalz"},{"index":547,"Unnamed: 0":547,"Jahr":2004,"Einwohner":4061105,"Bundesland":"Rheinland-Pfalz"},{"index":548,"Unnamed: 0":548,"Jahr":2003,"Einwohner":4058682,"Bundesland":"Rheinland-Pfalz"},{"index":549,"Unnamed: 0":549,"Jahr":2002,"Einwohner":4057727,"Bundesland":"Rheinland-Pfalz"},{"index":550,"Unnamed: 0":550,"Jahr":2001,"Einwohner":4049066,"Bundesland":"Rheinland-Pfalz"},{"index":551,"Unnamed: 0":551,"Jahr":2000,"Einwohner":4034557,"Bundesland":"Rheinland-Pfalz"},{"index":552,"Unnamed: 0":552,"Jahr":1999,"Einwohner":4030773,"Bundesland":"Rheinland-Pfalz"},{"index":553,"Unnamed: 0":553,"Jahr":1998,"Einwohner":4024969,"Bundesland":"Rheinland-Pfalz"},{"index":554,"Unnamed: 0":554,"Jahr":1997,"Einwohner":4017828,"Bundesland":"Rheinland-Pfalz"},{"index":555,"Unnamed: 0":555,"Jahr":1996,"Einwohner":4000567,"Bundesland":"Rheinland-Pfalz"},{"index":556,"Unnamed: 0":556,"Jahr":1995,"Einwohner":3977919,"Bundesland":"Rheinland-Pfalz"},{"index":557,"Unnamed: 0":557,"Jahr":1994,"Einwohner":3951573,"Bundesland":"Rheinland-Pfalz"},{"index":558,"Unnamed: 0":558,"Jahr":1993,"Einwohner":3925863,"Bundesland":"Rheinland-Pfalz"},{"index":559,"Unnamed: 0":559,"Jahr":1992,"Einwohner":3880965,"Bundesland":"Rheinland-Pfalz"},{"index":560,"Unnamed: 0":560,"Jahr":1991,"Einwohner":3821235,"Bundesland":"Rheinland-Pfalz"},{"index":561,"Unnamed: 0":561,"Jahr":1990,"Einwohner":3763510,"Bundesland":"Rheinland-Pfalz"},{"index":562,"Unnamed: 0":562,"Jahr":1989,"Einwohner":3701661,"Bundesland":"Rheinland-Pfalz"},{"index":563,"Unnamed: 0":563,"Jahr":1988,"Einwohner":3653155,"Bundesland":"Rheinland-Pfalz"},{"index":564,"Unnamed: 0":564,"Jahr":1987,"Einwohner":3634557,"Bundesland":"Rheinland-Pfalz"},{"index":565,"Unnamed: 0":565,"Jahr":1986,"Einwohner":3611437,"Bundesland":"Rheinland-Pfalz"},{"index":566,"Unnamed: 0":566,"Jahr":1985,"Einwohner":3615049,"Bundesland":"Rheinland-Pfalz"},{"index":567,"Unnamed: 0":567,"Jahr":1984,"Einwohner":3623985,"Bundesland":"Rheinland-Pfalz"},{"index":568,"Unnamed: 0":568,"Jahr":1983,"Einwohner":3633488,"Bundesland":"Rheinland-Pfalz"},{"index":569,"Unnamed: 0":569,"Jahr":1982,"Einwohner":3636506,"Bundesland":"Rheinland-Pfalz"},{"index":570,"Unnamed: 0":570,"Jahr":1981,"Einwohner":3641229,"Bundesland":"Rheinland-Pfalz"},{"index":571,"Unnamed: 0":571,"Jahr":1980,"Einwohner":3642482,"Bundesland":"Rheinland-Pfalz"},{"index":572,"Unnamed: 0":572,"Jahr":1979,"Einwohner":3633195,"Bundesland":"Rheinland-Pfalz"},{"index":573,"Unnamed: 0":573,"Jahr":1978,"Einwohner":3630947,"Bundesland":"Rheinland-Pfalz"},{"index":574,"Unnamed: 0":574,"Jahr":1977,"Einwohner":3639291,"Bundesland":"Rheinland-Pfalz"},{"index":575,"Unnamed: 0":575,"Jahr":1976,"Einwohner":3649001,"Bundesland":"Rheinland-Pfalz"},{"index":576,"Unnamed: 0":576,"Jahr":1975,"Einwohner":3665777,"Bundesland":"Rheinland-Pfalz"},{"index":577,"Unnamed: 0":577,"Jahr":1974,"Einwohner":3688066,"Bundesland":"Rheinland-Pfalz"},{"index":578,"Unnamed: 0":578,"Jahr":1973,"Einwohner":3700787,"Bundesland":"Rheinland-Pfalz"},{"index":579,"Unnamed: 0":579,"Jahr":1972,"Einwohner":3690372,"Bundesland":"Rheinland-Pfalz"},{"index":580,"Unnamed: 0":580,"Jahr":1971,"Einwohner":3678519,"Bundesland":"Rheinland-Pfalz"},{"index":581,"Unnamed: 0":581,"Jahr":1970,"Einwohner":3658932,"Bundesland":"Rheinland-Pfalz"},{"index":582,"Unnamed: 0":582,"Jahr":1969,"Einwohner":3671275,"Bundesland":"Rheinland-Pfalz"},{"index":583,"Unnamed: 0":583,"Jahr":1968,"Einwohner":3644511,"Bundesland":"Rheinland-Pfalz"},{"index":584,"Unnamed: 0":584,"Jahr":1967,"Einwohner":3625428,"Bundesland":"Rheinland-Pfalz"},{"index":585,"Unnamed: 0":585,"Jahr":1966,"Einwohner":3612668,"Bundesland":"Rheinland-Pfalz"},{"index":586,"Unnamed: 0":586,"Jahr":1965,"Einwohner":3581993,"Bundesland":"Rheinland-Pfalz"},{"index":587,"Unnamed: 0":587,"Jahr":1964,"Einwohner":3545448,"Bundesland":"Rheinland-Pfalz"},{"index":588,"Unnamed: 0":588,"Jahr":1963,"Einwohner":3509511,"Bundesland":"Rheinland-Pfalz"},{"index":589,"Unnamed: 0":589,"Jahr":1962,"Einwohner":3474464,"Bundesland":"Rheinland-Pfalz"},{"index":590,"Unnamed: 0":590,"Jahr":1961,"Einwohner":3438528,"Bundesland":"Rheinland-Pfalz"},{"index":591,"Unnamed: 0":591,"Jahr":1960,"Einwohner":3411170,"Bundesland":"Rheinland-Pfalz"},{"index":592,"Unnamed: 0":592,"Jahr":1959,"Einwohner":3377365,"Bundesland":"Rheinland-Pfalz"},{"index":593,"Unnamed: 0":593,"Jahr":1958,"Einwohner":3354672,"Bundesland":"Rheinland-Pfalz"},{"index":594,"Unnamed: 0":594,"Jahr":2022,"Einwohner":992666,"Bundesland":"Saarland"},{"index":595,"Unnamed: 0":595,"Jahr":2021,"Einwohner":982348,"Bundesland":"Saarland"},{"index":596,"Unnamed: 0":596,"Jahr":2020,"Einwohner":983991,"Bundesland":"Saarland"},{"index":597,"Unnamed: 0":597,"Jahr":2019,"Einwohner":986887,"Bundesland":"Saarland"},{"index":598,"Unnamed: 0":598,"Jahr":2018,"Einwohner":990509,"Bundesland":"Saarland"},{"index":599,"Unnamed: 0":599,"Jahr":2017,"Einwohner":994187,"Bundesland":"Saarland"},{"index":600,"Unnamed: 0":600,"Jahr":2016,"Einwohner":996651,"Bundesland":"Saarland"},{"index":601,"Unnamed: 0":601,"Jahr":2015,"Einwohner":995597,"Bundesland":"Saarland"},{"index":602,"Unnamed: 0":602,"Jahr":2014,"Einwohner":989035,"Bundesland":"Saarland"},{"index":603,"Unnamed: 0":603,"Jahr":2013,"Einwohner":990718,"Bundesland":"Saarland"},{"index":604,"Unnamed: 0":604,"Jahr":2012,"Einwohner":994287,"Bundesland":"Saarland"},{"index":605,"Unnamed: 0":605,"Jahr":2011,"Einwohner":997855,"Bundesland":"Saarland"},{"index":606,"Unnamed: 0":606,"Jahr":2010,"Einwohner":1017567,"Bundesland":"Saarland"},{"index":607,"Unnamed: 0":607,"Jahr":2009,"Einwohner":1022585,"Bundesland":"Saarland"},{"index":608,"Unnamed: 0":608,"Jahr":2008,"Einwohner":1030324,"Bundesland":"Saarland"},{"index":609,"Unnamed: 0":609,"Jahr":2007,"Einwohner":1036598,"Bundesland":"Saarland"},{"index":610,"Unnamed: 0":610,"Jahr":2006,"Einwohner":1043167,"Bundesland":"Saarland"},{"index":611,"Unnamed: 0":611,"Jahr":2005,"Einwohner":1050293,"Bundesland":"Saarland"},{"index":612,"Unnamed: 0":612,"Jahr":2004,"Einwohner":1056417,"Bundesland":"Saarland"},{"index":613,"Unnamed: 0":613,"Jahr":2003,"Einwohner":1061376,"Bundesland":"Saarland"},{"index":614,"Unnamed: 0":614,"Jahr":2002,"Einwohner":1064988,"Bundesland":"Saarland"},{"index":615,"Unnamed: 0":615,"Jahr":2001,"Einwohner":1066470,"Bundesland":"Saarland"},{"index":616,"Unnamed: 0":616,"Jahr":2000,"Einwohner":1068703,"Bundesland":"Saarland"},{"index":617,"Unnamed: 0":617,"Jahr":1999,"Einwohner":1071501,"Bundesland":"Saarland"},{"index":618,"Unnamed: 0":618,"Jahr":1998,"Einwohner":1074223,"Bundesland":"Saarland"},{"index":619,"Unnamed: 0":619,"Jahr":1997,"Einwohner":1080790,"Bundesland":"Saarland"},{"index":620,"Unnamed: 0":620,"Jahr":1996,"Einwohner":1084184,"Bundesland":"Saarland"},{"index":621,"Unnamed: 0":621,"Jahr":1995,"Einwohner":1084370,"Bundesland":"Saarland"},{"index":622,"Unnamed: 0":622,"Jahr":1994,"Einwohner":1084201,"Bundesland":"Saarland"},{"index":623,"Unnamed: 0":623,"Jahr":1993,"Einwohner":1084522,"Bundesland":"Saarland"},{"index":624,"Unnamed: 0":624,"Jahr":1992,"Einwohner":1084007,"Bundesland":"Saarland"},{"index":625,"Unnamed: 0":625,"Jahr":1991,"Einwohner":1076879,"Bundesland":"Saarland"},{"index":626,"Unnamed: 0":626,"Jahr":1990,"Einwohner":1072963,"Bundesland":"Saarland"},{"index":627,"Unnamed: 0":627,"Jahr":1989,"Einwohner":1064906,"Bundesland":"Saarland"},{"index":628,"Unnamed: 0":628,"Jahr":1988,"Einwohner":1054142,"Bundesland":"Saarland"},{"index":629,"Unnamed: 0":629,"Jahr":1987,"Einwohner":1054064,"Bundesland":"Saarland"},{"index":630,"Unnamed: 0":630,"Jahr":1986,"Einwohner":1042135,"Bundesland":"Saarland"},{"index":631,"Unnamed: 0":631,"Jahr":1985,"Einwohner":1045936,"Bundesland":"Saarland"},{"index":632,"Unnamed: 0":632,"Jahr":1984,"Einwohner":1050837,"Bundesland":"Saarland"},{"index":633,"Unnamed: 0":633,"Jahr":1983,"Einwohner":1052794,"Bundesland":"Saarland"},{"index":634,"Unnamed: 0":634,"Jahr":1982,"Einwohner":1057543,"Bundesland":"Saarland"},{"index":635,"Unnamed: 0":635,"Jahr":1981,"Einwohner":1063033,"Bundesland":"Saarland"},{"index":636,"Unnamed: 0":636,"Jahr":1980,"Einwohner":1066299,"Bundesland":"Saarland"},{"index":637,"Unnamed: 0":637,"Jahr":1979,"Einwohner":1068555,"Bundesland":"Saarland"},{"index":638,"Unnamed: 0":638,"Jahr":1978,"Einwohner":1072953,"Bundesland":"Saarland"},{"index":639,"Unnamed: 0":639,"Jahr":1977,"Einwohner":1081074,"Bundesland":"Saarland"},{"index":640,"Unnamed: 0":640,"Jahr":1976,"Einwohner":1088961,"Bundesland":"Saarland"},{"index":641,"Unnamed: 0":641,"Jahr":1975,"Einwohner":1096333,"Bundesland":"Saarland"},{"index":642,"Unnamed: 0":642,"Jahr":1974,"Einwohner":1103255,"Bundesland":"Saarland"},{"index":643,"Unnamed: 0":643,"Jahr":1973,"Einwohner":1111878,"Bundesland":"Saarland"},{"index":644,"Unnamed: 0":644,"Jahr":1972,"Einwohner":1118569,"Bundesland":"Saarland"},{"index":645,"Unnamed: 0":645,"Jahr":1971,"Einwohner":1121990,"Bundesland":"Saarland"},{"index":646,"Unnamed: 0":646,"Jahr":1970,"Einwohner":1121300,"Bundesland":"Saarland"},{"index":647,"Unnamed: 0":647,"Jahr":1969,"Einwohner":1127352,"Bundesland":"Saarland"},{"index":648,"Unnamed: 0":648,"Jahr":1968,"Einwohner":1128902,"Bundesland":"Saarland"},{"index":649,"Unnamed: 0":649,"Jahr":1967,"Einwohner":1131301,"Bundesland":"Saarland"},{"index":650,"Unnamed: 0":650,"Jahr":1966,"Einwohner":1132127,"Bundesland":"Saarland"},{"index":651,"Unnamed: 0":651,"Jahr":1965,"Einwohner":1127354,"Bundesland":"Saarland"},{"index":652,"Unnamed: 0":652,"Jahr":1964,"Einwohner":1117222,"Bundesland":"Saarland"},{"index":653,"Unnamed: 0":653,"Jahr":1963,"Einwohner":1106157,"Bundesland":"Saarland"},{"index":654,"Unnamed: 0":654,"Jahr":1962,"Einwohner":1096584,"Bundesland":"Saarland"},{"index":655,"Unnamed: 0":655,"Jahr":1961,"Einwohner":1083012,"Bundesland":"Saarland"},{"index":656,"Unnamed: 0":656,"Jahr":1960,"Einwohner":1060493,"Bundesland":"Saarland"},{"index":657,"Unnamed: 0":657,"Jahr":1959,"Einwohner":1040108,"Bundesland":"Saarland"},{"index":658,"Unnamed: 0":658,"Jahr":1958,"Einwohner":1040146,"Bundesland":"Saarland"},{"index":659,"Unnamed: 0":659,"Jahr":2022,"Einwohner":4086152,"Bundesland":"Sachsen"},{"index":660,"Unnamed: 0":660,"Jahr":2021,"Einwohner":4043002,"Bundesland":"Sachsen"},{"index":661,"Unnamed: 0":661,"Jahr":2020,"Einwohner":4056941,"Bundesland":"Sachsen"},{"index":662,"Unnamed: 0":662,"Jahr":2019,"Einwohner":4071971,"Bundesland":"Sachsen"},{"index":663,"Unnamed: 0":663,"Jahr":2018,"Einwohner":4077937,"Bundesland":"Sachsen"},{"index":664,"Unnamed: 0":664,"Jahr":2017,"Einwohner":4081308,"Bundesland":"Sachsen"},{"index":665,"Unnamed: 0":665,"Jahr":2016,"Einwohner":4081783,"Bundesland":"Sachsen"},{"index":666,"Unnamed: 0":666,"Jahr":2015,"Einwohner":4084851,"Bundesland":"Sachsen"},{"index":667,"Unnamed: 0":667,"Jahr":2014,"Einwohner":4055274,"Bundesland":"Sachsen"},{"index":668,"Unnamed: 0":668,"Jahr":2013,"Einwohner":4046385,"Bundesland":"Sachsen"},{"index":669,"Unnamed: 0":669,"Jahr":2012,"Einwohner":4050204,"Bundesland":"Sachsen"},{"index":670,"Unnamed: 0":670,"Jahr":2011,"Einwohner":4054182,"Bundesland":"Sachsen"},{"index":671,"Unnamed: 0":671,"Jahr":2010,"Einwohner":4149477,"Bundesland":"Sachsen"},{"index":672,"Unnamed: 0":672,"Jahr":2009,"Einwohner":4169000,"Bundesland":"Sachsen"},{"index":673,"Unnamed: 0":673,"Jahr":2008,"Einwohner":4193000,"Bundesland":"Sachsen"},{"index":674,"Unnamed: 0":674,"Jahr":2007,"Einwohner":4220000,"Bundesland":"Sachsen"},{"index":675,"Unnamed: 0":675,"Jahr":2006,"Einwohner":4250000,"Bundesland":"Sachsen"},{"index":676,"Unnamed: 0":676,"Jahr":2005,"Einwohner":4273754,"Bundesland":"Sachsen"},{"index":677,"Unnamed: 0":677,"Jahr":2004,"Einwohner":4296000,"Bundesland":"Sachsen"},{"index":678,"Unnamed: 0":678,"Jahr":2003,"Einwohner":4321000,"Bundesland":"Sachsen"},{"index":679,"Unnamed: 0":679,"Jahr":2002,"Einwohner":4349000,"Bundesland":"Sachsen"},{"index":680,"Unnamed: 0":680,"Jahr":2001,"Einwohner":4384000,"Bundesland":"Sachsen"},{"index":681,"Unnamed: 0":681,"Jahr":2000,"Einwohner":4425581,"Bundesland":"Sachsen"},{"index":682,"Unnamed: 0":682,"Jahr":1999,"Einwohner":4460000,"Bundesland":"Sachsen"},{"index":683,"Unnamed: 0":683,"Jahr":1998,"Einwohner":4489000,"Bundesland":"Sachsen"},{"index":684,"Unnamed: 0":684,"Jahr":1997,"Einwohner":4522000,"Bundesland":"Sachsen"},{"index":685,"Unnamed: 0":685,"Jahr":1996,"Einwohner":4546000,"Bundesland":"Sachsen"},{"index":686,"Unnamed: 0":686,"Jahr":1995,"Einwohner":4566603,"Bundesland":"Sachsen"},{"index":687,"Unnamed: 0":687,"Jahr":1994,"Einwohner":4584000,"Bundesland":"Sachsen"},{"index":688,"Unnamed: 0":688,"Jahr":1993,"Einwohner":4608000,"Bundesland":"Sachsen"},{"index":689,"Unnamed: 0":689,"Jahr":1992,"Einwohner":4641000,"Bundesland":"Sachsen"},{"index":690,"Unnamed: 0":690,"Jahr":1991,"Einwohner":4679000,"Bundesland":"Sachsen"},{"index":691,"Unnamed: 0":691,"Jahr":1990,"Einwohner":4764301,"Bundesland":"Sachsen"},{"index":692,"Unnamed: 0":692,"Jahr":1985,"Einwohner":5064000,"Bundesland":"Sachsen"},{"index":693,"Unnamed: 0":693,"Jahr":1980,"Einwohner":5174000,"Bundesland":"Sachsen"},{"index":694,"Unnamed: 0":694,"Jahr":1970,"Einwohner":5419000,"Bundesland":"Sachsen"},{"index":695,"Unnamed: 0":695,"Jahr":1961,"Einwohner":5450000,"Bundesland":"Sachsen"},{"index":696,"Unnamed: 0":696,"Jahr":2022,"Einwohner":2186643,"Bundesland":"Sachsen-Anhalt"},{"index":697,"Unnamed: 0":697,"Jahr":2021,"Einwohner":2169253,"Bundesland":"Sachsen-Anhalt"},{"index":698,"Unnamed: 0":698,"Jahr":2020,"Einwohner":2180684,"Bundesland":"Sachsen-Anhalt"},{"index":699,"Unnamed: 0":699,"Jahr":2019,"Einwohner":2194782,"Bundesland":"Sachsen-Anhalt"},{"index":700,"Unnamed: 0":700,"Jahr":2018,"Einwohner":2208321,"Bundesland":"Sachsen-Anhalt"},{"index":701,"Unnamed: 0":701,"Jahr":2017,"Einwohner":2223081,"Bundesland":"Sachsen-Anhalt"},{"index":702,"Unnamed: 0":702,"Jahr":2016,"Einwohner":2236252,"Bundesland":"Sachsen-Anhalt"},{"index":703,"Unnamed: 0":703,"Jahr":2015,"Einwohner":2245470,"Bundesland":"Sachsen-Anhalt"},{"index":704,"Unnamed: 0":704,"Jahr":2014,"Einwohner":2235548,"Bundesland":"Sachsen-Anhalt"},{"index":705,"Unnamed: 0":705,"Jahr":2013,"Einwohner":2244577,"Bundesland":"Sachsen-Anhalt"},{"index":706,"Unnamed: 0":706,"Jahr":2012,"Einwohner":2259393,"Bundesland":"Sachsen-Anhalt"},{"index":707,"Unnamed: 0":707,"Jahr":2011,"Einwohner":2276736,"Bundesland":"Sachsen-Anhalt"},{"index":708,"Unnamed: 0":708,"Jahr":2010,"Einwohner":2335006,"Bundesland":"Sachsen-Anhalt"},{"index":709,"Unnamed: 0":709,"Jahr":2009,"Einwohner":2356,"Bundesland":"Sachsen-Anhalt"},{"index":710,"Unnamed: 0":710,"Jahr":2008,"Einwohner":2382,"Bundesland":"Sachsen-Anhalt"},{"index":711,"Unnamed: 0":711,"Jahr":2007,"Einwohner":2412,"Bundesland":"Sachsen-Anhalt"},{"index":712,"Unnamed: 0":712,"Jahr":2006,"Einwohner":2442,"Bundesland":"Sachsen-Anhalt"},{"index":713,"Unnamed: 0":713,"Jahr":2005,"Einwohner":2469716,"Bundesland":"Sachsen-Anhalt"},{"index":714,"Unnamed: 0":714,"Jahr":2004,"Einwohner":2494,"Bundesland":"Sachsen-Anhalt"},{"index":715,"Unnamed: 0":715,"Jahr":2003,"Einwohner":2523,"Bundesland":"Sachsen-Anhalt"},{"index":716,"Unnamed: 0":716,"Jahr":2002,"Einwohner":2549,"Bundesland":"Sachsen-Anhalt"},{"index":717,"Unnamed: 0":717,"Jahr":2001,"Einwohner":2581,"Bundesland":"Sachsen-Anhalt"},{"index":718,"Unnamed: 0":718,"Jahr":2000,"Einwohner":2615375,"Bundesland":"Sachsen-Anhalt"},{"index":719,"Unnamed: 0":719,"Jahr":1999,"Einwohner":2649,"Bundesland":"Sachsen-Anhalt"},{"index":720,"Unnamed: 0":720,"Jahr":1998,"Einwohner":2674,"Bundesland":"Sachsen-Anhalt"},{"index":721,"Unnamed: 0":721,"Jahr":1997,"Einwohner":2702,"Bundesland":"Sachsen-Anhalt"},{"index":722,"Unnamed: 0":722,"Jahr":1996,"Einwohner":2724,"Bundesland":"Sachsen-Anhalt"},{"index":723,"Unnamed: 0":723,"Jahr":1995,"Einwohner":2738928,"Bundesland":"Sachsen-Anhalt"},{"index":724,"Unnamed: 0":724,"Jahr":1994,"Einwohner":2759,"Bundesland":"Sachsen-Anhalt"},{"index":725,"Unnamed: 0":725,"Jahr":1993,"Einwohner":2778,"Bundesland":"Sachsen-Anhalt"},{"index":726,"Unnamed: 0":726,"Jahr":1992,"Einwohner":2797,"Bundesland":"Sachsen-Anhalt"},{"index":727,"Unnamed: 0":727,"Jahr":1991,"Einwohner":2823,"Bundesland":"Sachsen-Anhalt"},{"index":728,"Unnamed: 0":728,"Jahr":1990,"Einwohner":2873957,"Bundesland":"Sachsen-Anhalt"},{"index":729,"Unnamed: 0":729,"Jahr":1985,"Einwohner":3021000,"Bundesland":"Sachsen-Anhalt"},{"index":730,"Unnamed: 0":730,"Jahr":1980,"Einwohner":3078000,"Bundesland":"Sachsen-Anhalt"},{"index":731,"Unnamed: 0":731,"Jahr":1970,"Einwohner":3218000,"Bundesland":"Sachsen-Anhalt"},{"index":732,"Unnamed: 0":732,"Jahr":1961,"Einwohner":3300000,"Bundesland":"Sachsen-Anhalt"},{"index":733,"Unnamed: 0":733,"Jahr":2022,"Einwohner":2126846,"Bundesland":"Thüringen"},{"index":734,"Unnamed: 0":734,"Jahr":2021,"Einwohner":2108863,"Bundesland":"Thüringen"},{"index":735,"Unnamed: 0":735,"Jahr":2020,"Einwohner":2120237,"Bundesland":"Thüringen"},{"index":736,"Unnamed: 0":736,"Jahr":2019,"Einwohner":2133378,"Bundesland":"Thüringen"},{"index":737,"Unnamed: 0":737,"Jahr":2018,"Einwohner":2143145,"Bundesland":"Thüringen"},{"index":738,"Unnamed: 0":738,"Jahr":2017,"Einwohner":2151205,"Bundesland":"Thüringen"},{"index":739,"Unnamed: 0":739,"Jahr":2016,"Einwohner":2158128,"Bundesland":"Thüringen"},{"index":740,"Unnamed: 0":740,"Jahr":2015,"Einwohner":2170714,"Bundesland":"Thüringen"},{"index":741,"Unnamed: 0":741,"Jahr":2014,"Einwohner":2156759,"Bundesland":"Thüringen"},{"index":742,"Unnamed: 0":742,"Jahr":2013,"Einwohner":2160840,"Bundesland":"Thüringen"},{"index":743,"Unnamed: 0":743,"Jahr":2012,"Einwohner":2170460,"Bundesland":"Thüringen"},{"index":744,"Unnamed: 0":744,"Jahr":2011,"Einwohner":2181603,"Bundesland":"Thüringen"},{"index":745,"Unnamed: 0":745,"Jahr":2010,"Einwohner":2235025,"Bundesland":"Thüringen"},{"index":746,"Unnamed: 0":746,"Jahr":2009,"Einwohner":2250000,"Bundesland":"Thüringen"},{"index":747,"Unnamed: 0":747,"Jahr":2008,"Einwohner":2268000,"Bundesland":"Thüringen"},{"index":748,"Unnamed: 0":748,"Jahr":2007,"Einwohner":2289000,"Bundesland":"Thüringen"},{"index":749,"Unnamed: 0":749,"Jahr":2006,"Einwohner":2311000,"Bundesland":"Thüringen"},{"index":750,"Unnamed: 0":750,"Jahr":2005,"Einwohner":2334575,"Bundesland":"Thüringen"},{"index":751,"Unnamed: 0":751,"Jahr":2004,"Einwohner":2355000,"Bundesland":"Thüringen"},{"index":752,"Unnamed: 0":752,"Jahr":2003,"Einwohner":2373000,"Bundesland":"Thüringen"},{"index":753,"Unnamed: 0":753,"Jahr":2002,"Einwohner":2392000,"Bundesland":"Thüringen"},{"index":754,"Unnamed: 0":754,"Jahr":2001,"Einwohner":2411000,"Bundesland":"Thüringen"},{"index":755,"Unnamed: 0":755,"Jahr":2000,"Einwohner":2431255,"Bundesland":"Thüringen"},{"index":756,"Unnamed: 0":756,"Jahr":1999,"Einwohner":2449000,"Bundesland":"Thüringen"},{"index":757,"Unnamed: 0":757,"Jahr":1998,"Einwohner":2463000,"Bundesland":"Thüringen"},{"index":758,"Unnamed: 0":758,"Jahr":1997,"Einwohner":2478000,"Bundesland":"Thüringen"},{"index":759,"Unnamed: 0":759,"Jahr":1996,"Einwohner":2491000,"Bundesland":"Thüringen"},{"index":760,"Unnamed: 0":760,"Jahr":1995,"Einwohner":2503785,"Bundesland":"Thüringen"},{"index":761,"Unnamed: 0":761,"Jahr":1994,"Einwohner":2518000,"Bundesland":"Thüringen"},{"index":762,"Unnamed: 0":762,"Jahr":1993,"Einwohner":2533000,"Bundesland":"Thüringen"},{"index":763,"Unnamed: 0":763,"Jahr":1992,"Einwohner":2546000,"Bundesland":"Thüringen"},{"index":764,"Unnamed: 0":764,"Jahr":1991,"Einwohner":2572000,"Bundesland":"Thüringen"},{"index":765,"Unnamed: 0":765,"Jahr":1990,"Einwohner":2611319,"Bundesland":"Thüringen"},{"index":766,"Unnamed: 0":766,"Jahr":1985,"Einwohner":2722000,"Bundesland":"Thüringen"},{"index":767,"Unnamed: 0":767,"Jahr":1980,"Einwohner":2730000,"Bundesland":"Thüringen"},{"index":768,"Unnamed: 0":768,"Jahr":1970,"Einwohner":2759000,"Bundesland":"Thüringen"},{"index":769,"Unnamed: 0":769,"Jahr":1961,"Einwohner":2725000,"Bundesland":"Thüringen"},{"index":770,"Unnamed: 0":770,"Jahr":2022,"Einwohner":1892122,"Bundesland":"Hamburg"},{"index":771,"Unnamed: 0":771,"Jahr":2021,"Einwohner":1853935,"Bundesland":"Hamburg"},{"index":772,"Unnamed: 0":772,"Jahr":2020,"Einwohner":1852478,"Bundesland":"Hamburg"},{"index":773,"Unnamed: 0":773,"Jahr":2019,"Einwohner":1847253,"Bundesland":"Hamburg"},{"index":774,"Unnamed: 0":774,"Jahr":2018,"Einwohner":1841179,"Bundesland":"Hamburg"},{"index":775,"Unnamed: 0":775,"Jahr":2017,"Einwohner":1830584,"Bundesland":"Hamburg"},{"index":776,"Unnamed: 0":776,"Jahr":2016,"Einwohner":1810438,"Bundesland":"Hamburg"},{"index":777,"Unnamed: 0":777,"Jahr":2015,"Einwohner":1787408,"Bundesland":"Hamburg"},{"index":778,"Unnamed: 0":778,"Jahr":2014,"Einwohner":1762791,"Bundesland":"Hamburg"},{"index":779,"Unnamed: 0":779,"Jahr":2013,"Einwohner":1746342,"Bundesland":"Hamburg"},{"index":780,"Unnamed: 0":780,"Jahr":2012,"Einwohner":1734272,"Bundesland":"Hamburg"},{"index":781,"Unnamed: 0":781,"Jahr":2011,"Einwohner":1718187,"Bundesland":"Hamburg"},{"index":782,"Unnamed: 0":782,"Jahr":2010,"Einwohner":1786448,"Bundesland":"Hamburg"},{"index":783,"Unnamed: 0":783,"Jahr":2009,"Einwohner":1774224,"Bundesland":"Hamburg"},{"index":784,"Unnamed: 0":784,"Jahr":2008,"Einwohner":1772100,"Bundesland":"Hamburg"},{"index":785,"Unnamed: 0":785,"Jahr":2007,"Einwohner":1770629,"Bundesland":"Hamburg"},{"index":786,"Unnamed: 0":786,"Jahr":2006,"Einwohner":1754182,"Bundesland":"Hamburg"},{"index":787,"Unnamed: 0":787,"Jahr":2005,"Einwohner":1743627,"Bundesland":"Hamburg"},{"index":788,"Unnamed: 0":788,"Jahr":2004,"Einwohner":1734830,"Bundesland":"Hamburg"},{"index":789,"Unnamed: 0":789,"Jahr":2003,"Einwohner":1734083,"Bundesland":"Hamburg"},{"index":790,"Unnamed: 0":790,"Jahr":2002,"Einwohner":1728806,"Bundesland":"Hamburg"},{"index":791,"Unnamed: 0":791,"Jahr":2001,"Einwohner":1726363,"Bundesland":"Hamburg"},{"index":792,"Unnamed: 0":792,"Jahr":2000,"Einwohner":1715392,"Bundesland":"Hamburg"},{"index":793,"Unnamed: 0":793,"Jahr":1999,"Einwohner":1704735,"Bundesland":"Hamburg"},{"index":794,"Unnamed: 0":794,"Jahr":1998,"Einwohner":1700089,"Bundesland":"Hamburg"},{"index":795,"Unnamed: 0":795,"Jahr":1997,"Einwohner":1704731,"Bundesland":"Hamburg"},{"index":796,"Unnamed: 0":796,"Jahr":1996,"Einwohner":1707986,"Bundesland":"Hamburg"},{"index":797,"Unnamed: 0":797,"Jahr":1995,"Einwohner":1707901,"Bundesland":"Hamburg"},{"index":798,"Unnamed: 0":798,"Jahr":1994,"Einwohner":1705872,"Bundesland":"Hamburg"},{"index":799,"Unnamed: 0":799,"Jahr":1993,"Einwohner":1702887,"Bundesland":"Hamburg"},{"index":800,"Unnamed: 0":800,"Jahr":1992,"Einwohner":1688785,"Bundesland":"Hamburg"},{"index":801,"Unnamed: 0":801,"Jahr":1991,"Einwohner":1668757,"Bundesland":"Hamburg"},{"index":802,"Unnamed: 0":802,"Jahr":1990,"Einwohner":1652363,"Bundesland":"Hamburg"},{"index":803,"Unnamed: 0":803,"Jahr":1989,"Einwohner":1626220,"Bundesland":"Hamburg"},{"index":804,"Unnamed: 0":804,"Jahr":1988,"Einwohner":1603070,"Bundesland":"Hamburg"},{"index":805,"Unnamed: 0":805,"Jahr":1987,"Einwohner":1594190,"Bundesland":"Hamburg"},{"index":806,"Unnamed: 0":806,"Jahr":1986,"Einwohner":1571267,"Bundesland":"Hamburg"},{"index":807,"Unnamed: 0":807,"Jahr":1985,"Einwohner":1579884,"Bundesland":"Hamburg"},{"index":808,"Unnamed: 0":808,"Jahr":1984,"Einwohner":1592447,"Bundesland":"Hamburg"},{"index":809,"Unnamed: 0":809,"Jahr":1983,"Einwohner":1609531,"Bundesland":"Hamburg"},{"index":810,"Unnamed: 0":810,"Jahr":1982,"Einwohner":1623848,"Bundesland":"Hamburg"},{"index":811,"Unnamed: 0":811,"Jahr":1981,"Einwohner":1637132,"Bundesland":"Hamburg"},{"index":812,"Unnamed: 0":812,"Jahr":1980,"Einwohner":1645095,"Bundesland":"Hamburg"},{"index":813,"Unnamed: 0":813,"Jahr":1979,"Einwohner":1653043,"Bundesland":"Hamburg"},{"index":814,"Unnamed: 0":814,"Jahr":1978,"Einwohner":1664305,"Bundesland":"Hamburg"},{"index":815,"Unnamed: 0":815,"Jahr":1977,"Einwohner":1680340,"Bundesland":"Hamburg"},{"index":816,"Unnamed: 0":816,"Jahr":1976,"Einwohner":1698615,"Bundesland":"Hamburg"},{"index":817,"Unnamed: 0":817,"Jahr":1975,"Einwohner":1717383,"Bundesland":"Hamburg"},{"index":818,"Unnamed: 0":818,"Jahr":1974,"Einwohner":1733802,"Bundesland":"Hamburg"},{"index":819,"Unnamed: 0":819,"Jahr":1973,"Einwohner":1751621,"Bundesland":"Hamburg"},{"index":820,"Unnamed: 0":820,"Jahr":1972,"Einwohner":1766214,"Bundesland":"Hamburg"},{"index":821,"Unnamed: 0":821,"Jahr":1971,"Einwohner":1781621,"Bundesland":"Hamburg"},{"index":822,"Unnamed: 0":822,"Jahr":1970,"Einwohner":1793640,"Bundesland":"Hamburg"},{"index":823,"Unnamed: 0":823,"Jahr":1969,"Einwohner":1817122,"Bundesland":"Hamburg"},{"index":824,"Unnamed: 0":824,"Jahr":1968,"Einwohner":1822837,"Bundesland":"Hamburg"},{"index":825,"Unnamed: 0":825,"Jahr":1967,"Einwohner":1832560,"Bundesland":"Hamburg"},{"index":826,"Unnamed: 0":826,"Jahr":1966,"Einwohner":1847267,"Bundesland":"Hamburg"},{"index":827,"Unnamed: 0":827,"Jahr":1965,"Einwohner":1854361,"Bundesland":"Hamburg"},{"index":828,"Unnamed: 0":828,"Jahr":1964,"Einwohner":1857431,"Bundesland":"Hamburg"},{"index":829,"Unnamed: 0":829,"Jahr":1963,"Einwohner":1854637,"Bundesland":"Hamburg"},{"index":830,"Unnamed: 0":830,"Jahr":1962,"Einwohner":1847495,"Bundesland":"Hamburg"},{"index":831,"Unnamed: 0":831,"Jahr":1961,"Einwohner":1840515,"Bundesland":"Hamburg"},{"index":832,"Unnamed: 0":832,"Jahr":1960,"Einwohner":1836958,"Bundesland":"Hamburg"},{"index":833,"Unnamed: 0":833,"Jahr":1959,"Einwohner":1823574,"Bundesland":"Hamburg"},{"index":834,"Unnamed: 0":834,"Jahr":1958,"Einwohner":1807640,"Bundesland":"Hamburg"},{"index":835,"Unnamed: 0":835,"Jahr":2022,"Einwohner":2953270,"Bundesland":"Schleswig-Holstein"},{"index":836,"Unnamed: 0":836,"Jahr":2021,"Einwohner":2922005,"Bundesland":"Schleswig-Holstein"},{"index":837,"Unnamed: 0":837,"Jahr":2020,"Einwohner":2910875,"Bundesland":"Schleswig-Holstein"},{"index":838,"Unnamed: 0":838,"Jahr":2019,"Einwohner":2903773,"Bundesland":"Schleswig-Holstein"},{"index":839,"Unnamed: 0":839,"Jahr":2018,"Einwohner":2896712,"Bundesland":"Schleswig-Holstein"},{"index":840,"Unnamed: 0":840,"Jahr":2017,"Einwohner":2889821,"Bundesland":"Schleswig-Holstein"},{"index":841,"Unnamed: 0":841,"Jahr":2016,"Einwohner":2881926,"Bundesland":"Schleswig-Holstein"},{"index":842,"Unnamed: 0":842,"Jahr":2015,"Einwohner":2858714,"Bundesland":"Schleswig-Holstein"},{"index":843,"Unnamed: 0":843,"Jahr":2014,"Einwohner":2830864,"Bundesland":"Schleswig-Holstein"},{"index":844,"Unnamed: 0":844,"Jahr":2013,"Einwohner":2815955,"Bundesland":"Schleswig-Holstein"},{"index":845,"Unnamed: 0":845,"Jahr":2012,"Einwohner":2806531,"Bundesland":"Schleswig-Holstein"},{"index":846,"Unnamed: 0":846,"Jahr":2011,"Einwohner":2802266,"Bundesland":"Schleswig-Holstein"},{"index":847,"Unnamed: 0":847,"Jahr":2010,"Einwohner":2834259,"Bundesland":"Schleswig-Holstein"},{"index":848,"Unnamed: 0":848,"Jahr":2009,"Einwohner":2832027,"Bundesland":"Schleswig-Holstein"},{"index":849,"Unnamed: 0":849,"Jahr":2008,"Einwohner":2834260,"Bundesland":"Schleswig-Holstein"},{"index":850,"Unnamed: 0":850,"Jahr":2007,"Einwohner":2837373,"Bundesland":"Schleswig-Holstein"},{"index":851,"Unnamed: 0":851,"Jahr":2006,"Einwohner":2834254,"Bundesland":"Schleswig-Holstein"},{"index":852,"Unnamed: 0":852,"Jahr":2005,"Einwohner":2832950,"Bundesland":"Schleswig-Holstein"},{"index":853,"Unnamed: 0":853,"Jahr":2004,"Einwohner":2828760,"Bundesland":"Schleswig-Holstein"},{"index":854,"Unnamed: 0":854,"Jahr":2003,"Einwohner":2823171,"Bundesland":"Schleswig-Holstein"},{"index":855,"Unnamed: 0":855,"Jahr":2002,"Einwohner":2816507,"Bundesland":"Schleswig-Holstein"},{"index":856,"Unnamed: 0":856,"Jahr":2001,"Einwohner":2804249,"Bundesland":"Schleswig-Holstein"},{"index":857,"Unnamed: 0":857,"Jahr":2000,"Einwohner":2789761,"Bundesland":"Schleswig-Holstein"},{"index":858,"Unnamed: 0":858,"Jahr":1999,"Einwohner":2777275,"Bundesland":"Schleswig-Holstein"},{"index":859,"Unnamed: 0":859,"Jahr":1998,"Einwohner":2766057,"Bundesland":"Schleswig-Holstein"},{"index":860,"Unnamed: 0":860,"Jahr":1997,"Einwohner":2756473,"Bundesland":"Schleswig-Holstein"},{"index":861,"Unnamed: 0":861,"Jahr":1996,"Einwohner":2742293,"Bundesland":"Schleswig-Holstein"},{"index":862,"Unnamed: 0":862,"Jahr":1995,"Einwohner":2725461,"Bundesland":"Schleswig-Holstein"},{"index":863,"Unnamed: 0":863,"Jahr":1994,"Einwohner":2708392,"Bundesland":"Schleswig-Holstein"},{"index":864,"Unnamed: 0":864,"Jahr":1993,"Einwohner":2694875,"Bundesland":"Schleswig-Holstein"},{"index":865,"Unnamed: 0":865,"Jahr":1992,"Einwohner":2679575,"Bundesland":"Schleswig-Holstein"},{"index":866,"Unnamed: 0":866,"Jahr":1991,"Einwohner":2648532,"Bundesland":"Schleswig-Holstein"},{"index":867,"Unnamed: 0":867,"Jahr":1990,"Einwohner":2626127,"Bundesland":"Schleswig-Holstein"},{"index":868,"Unnamed: 0":868,"Jahr":1989,"Einwohner":2594606,"Bundesland":"Schleswig-Holstein"},{"index":869,"Unnamed: 0":869,"Jahr":1988,"Einwohner":2564565,"Bundesland":"Schleswig-Holstein"},{"index":870,"Unnamed: 0":870,"Jahr":1987,"Einwohner":2555278,"Bundesland":"Schleswig-Holstein"},{"index":871,"Unnamed: 0":871,"Jahr":1986,"Einwohner":2612672,"Bundesland":"Schleswig-Holstein"},{"index":872,"Unnamed: 0":872,"Jahr":1985,"Einwohner":2614151,"Bundesland":"Schleswig-Holstein"},{"index":873,"Unnamed: 0":873,"Jahr":1984,"Einwohner":2613796,"Bundesland":"Schleswig-Holstein"},{"index":874,"Unnamed: 0":874,"Jahr":1983,"Einwohner":2616598,"Bundesland":"Schleswig-Holstein"},{"index":875,"Unnamed: 0":875,"Jahr":1982,"Einwohner":2618156,"Bundesland":"Schleswig-Holstein"},{"index":876,"Unnamed: 0":876,"Jahr":1981,"Einwohner":2619186,"Bundesland":"Schleswig-Holstein"},{"index":877,"Unnamed: 0":877,"Jahr":1980,"Einwohner":2611285,"Bundesland":"Schleswig-Holstein"},{"index":878,"Unnamed: 0":878,"Jahr":1979,"Einwohner":2599004,"Bundesland":"Schleswig-Holstein"},{"index":879,"Unnamed: 0":879,"Jahr":1978,"Einwohner":2591285,"Bundesland":"Schleswig-Holstein"},{"index":880,"Unnamed: 0":880,"Jahr":1977,"Einwohner":2587183,"Bundesland":"Schleswig-Holstein"},{"index":881,"Unnamed: 0":881,"Jahr":1976,"Einwohner":2582718,"Bundesland":"Schleswig-Holstein"},{"index":882,"Unnamed: 0":882,"Jahr":1975,"Einwohner":2582412,"Bundesland":"Schleswig-Holstein"},{"index":883,"Unnamed: 0":883,"Jahr":1974,"Einwohner":2584343,"Bundesland":"Schleswig-Holstein"},{"index":884,"Unnamed: 0":884,"Jahr":1973,"Einwohner":2579598,"Bundesland":"Schleswig-Holstein"},{"index":885,"Unnamed: 0":885,"Jahr":1972,"Einwohner":2563775,"Bundesland":"Schleswig-Holstein"},{"index":886,"Unnamed: 0":886,"Jahr":1971,"Einwohner":2543236,"Bundesland":"Schleswig-Holstein"},{"index":887,"Unnamed: 0":887,"Jahr":1970,"Einwohner":2510608,"Bundesland":"Schleswig-Holstein"},{"index":888,"Unnamed: 0":888,"Jahr":1969,"Einwohner":2557245,"Bundesland":"Schleswig-Holstein"},{"index":889,"Unnamed: 0":889,"Jahr":1968,"Einwohner":2528733,"Bundesland":"Schleswig-Holstein"},{"index":890,"Unnamed: 0":890,"Jahr":1967,"Einwohner":2499730,"Bundesland":"Schleswig-Holstein"},{"index":891,"Unnamed: 0":891,"Jahr":1966,"Einwohner":2472526,"Bundesland":"Schleswig-Holstein"},{"index":892,"Unnamed: 0":892,"Jahr":1965,"Einwohner":2438829,"Bundesland":"Schleswig-Holstein"},{"index":893,"Unnamed: 0":893,"Jahr":1964,"Einwohner":2405547,"Bundesland":"Schleswig-Holstein"},{"index":894,"Unnamed: 0":894,"Jahr":1963,"Einwohner":2375783,"Bundesland":"Schleswig-Holstein"},{"index":895,"Unnamed: 0":895,"Jahr":1962,"Einwohner":2351315,"Bundesland":"Schleswig-Holstein"},{"index":896,"Unnamed: 0":896,"Jahr":1961,"Einwohner":2329247,"Bundesland":"Schleswig-Holstein"},{"index":897,"Unnamed: 0":897,"Jahr":1960,"Einwohner":2309409,"Bundesland":"Schleswig-Holstein"},{"index":898,"Unnamed: 0":898,"Jahr":1959,"Einwohner":2289894,"Bundesland":"Schleswig-Holstein"},{"index":899,"Unnamed: 0":899,"Jahr":1958,"Einwohner":2275802,"Bundesland":"Schleswig-Holstein"},{"index":900,"Unnamed: 0":900,"Jahr":2022,"Einwohner":84359000,"Bundesland":"Deutschland"},{"index":901,"Unnamed: 0":901,"Jahr":2021,"Einwohner":83237000,"Bundesland":"Deutschland"},{"index":902,"Unnamed: 0":902,"Jahr":2020,"Einwohner":83155000,"Bundesland":"Deutschland"},{"index":903,"Unnamed: 0":903,"Jahr":2019,"Einwohner":83167000,"Bundesland":"Deutschland"},{"index":904,"Unnamed: 0":904,"Jahr":2018,"Einwohner":83019000,"Bundesland":"Deutschland"},{"index":905,"Unnamed: 0":905,"Jahr":2017,"Einwohner":82792000,"Bundesland":"Deutschland"},{"index":906,"Unnamed: 0":906,"Jahr":2016,"Einwohner":82522000,"Bundesland":"Deutschland"},{"index":907,"Unnamed: 0":907,"Jahr":2015,"Einwohner":82176000,"Bundesland":"Deutschland"},{"index":908,"Unnamed: 0":908,"Jahr":2014,"Einwohner":81198000,"Bundesland":"Deutschland"},{"index":909,"Unnamed: 0":909,"Jahr":2013,"Einwohner":80767000,"Bundesland":"Deutschland"},{"index":910,"Unnamed: 0":910,"Jahr":2012,"Einwohner":80524000,"Bundesland":"Deutschland"},{"index":911,"Unnamed: 0":911,"Jahr":2011,"Einwohner":80328000,"Bundesland":"Deutschland"},{"index":912,"Unnamed: 0":912,"Jahr":2010,"Einwohner":81752000,"Bundesland":"Deutschland"},{"index":913,"Unnamed: 0":913,"Jahr":2009,"Einwohner":81802000,"Bundesland":"Deutschland"},{"index":914,"Unnamed: 0":914,"Jahr":2008,"Einwohner":82002000,"Bundesland":"Deutschland"},{"index":915,"Unnamed: 0":915,"Jahr":2007,"Einwohner":82218000,"Bundesland":"Deutschland"},{"index":916,"Unnamed: 0":916,"Jahr":2006,"Einwohner":82315000,"Bundesland":"Deutschland"},{"index":917,"Unnamed: 0":917,"Jahr":2005,"Einwohner":82438000,"Bundesland":"Deutschland"},{"index":918,"Unnamed: 0":918,"Jahr":2004,"Einwohner":82501000,"Bundesland":"Deutschland"},{"index":919,"Unnamed: 0":919,"Jahr":2003,"Einwohner":82532000,"Bundesland":"Deutschland"},{"index":920,"Unnamed: 0":920,"Jahr":2002,"Einwohner":82537000,"Bundesland":"Deutschland"},{"index":921,"Unnamed: 0":921,"Jahr":2001,"Einwohner":82440000,"Bundesland":"Deutschland"},{"index":922,"Unnamed: 0":922,"Jahr":2000,"Einwohner":82260000,"Bundesland":"Deutschland"},{"index":923,"Unnamed: 0":923,"Jahr":1999,"Einwohner":82163000,"Bundesland":"Deutschland"},{"index":924,"Unnamed: 0":924,"Jahr":1998,"Einwohner":82037000,"Bundesland":"Deutschland"},{"index":925,"Unnamed: 0":925,"Jahr":1997,"Einwohner":82057000,"Bundesland":"Deutschland"},{"index":926,"Unnamed: 0":926,"Jahr":1996,"Einwohner":82012000,"Bundesland":"Deutschland"},{"index":927,"Unnamed: 0":927,"Jahr":1995,"Einwohner":81817000,"Bundesland":"Deutschland"},{"index":928,"Unnamed: 0":928,"Jahr":1994,"Einwohner":81539000,"Bundesland":"Deutschland"},{"index":929,"Unnamed: 0":929,"Jahr":1993,"Einwohner":81338000,"Bundesland":"Deutschland"},{"index":930,"Unnamed: 0":930,"Jahr":1992,"Einwohner":80975000,"Bundesland":"Deutschland"},{"index":931,"Unnamed: 0":931,"Jahr":1991,"Einwohner":80275000,"Bundesland":"Deutschland"},{"index":932,"Unnamed: 0":932,"Jahr":1990,"Einwohner":79753000,"Bundesland":"Deutschland"},{"index":933,"Unnamed: 0":933,"Jahr":1989,"Einwohner":79113000,"Bundesland":"Deutschland"},{"index":934,"Unnamed: 0":934,"Jahr":1988,"Einwohner":78390000,"Bundesland":"Deutschland"},{"index":935,"Unnamed: 0":935,"Jahr":1986,"Einwohner":77780000,"Bundesland":"Deutschland"},{"index":936,"Unnamed: 0":936,"Jahr":1985,"Einwohner":77661000,"Bundesland":"Deutschland"},{"index":937,"Unnamed: 0":937,"Jahr":1984,"Einwohner":77709000,"Bundesland":"Deutschland"},{"index":938,"Unnamed: 0":938,"Jahr":1983,"Einwohner":78008000,"Bundesland":"Deutschland"},{"index":939,"Unnamed: 0":939,"Jahr":1982,"Einwohner":78248000,"Bundesland":"Deutschland"},{"index":940,"Unnamed: 0":940,"Jahr":1981,"Einwohner":78418000,"Bundesland":"Deutschland"},{"index":941,"Unnamed: 0":941,"Jahr":1980,"Einwohner":78397000,"Bundesland":"Deutschland"},{"index":942,"Unnamed: 0":942,"Jahr":1979,"Einwohner":78180000,"Bundesland":"Deutschland"},{"index":943,"Unnamed: 0":943,"Jahr":1978,"Einwohner":78073000,"Bundesland":"Deutschland"},{"index":944,"Unnamed: 0":944,"Jahr":1977,"Einwohner":78111000,"Bundesland":"Deutschland"},{"index":945,"Unnamed: 0":945,"Jahr":1976,"Einwohner":78209000,"Bundesland":"Deutschland"},{"index":946,"Unnamed: 0":946,"Jahr":1975,"Einwohner":78465000,"Bundesland":"Deutschland"},{"index":947,"Unnamed: 0":947,"Jahr":1974,"Einwohner":78882000,"Bundesland":"Deutschland"},{"index":948,"Unnamed: 0":948,"Jahr":1973,"Einwohner":79053000,"Bundesland":"Deutschland"},{"index":949,"Unnamed: 0":949,"Jahr":1972,"Einwohner":78821000,"Bundesland":"Deutschland"},{"index":950,"Unnamed: 0":950,"Jahr":1971,"Einwohner":78556000,"Bundesland":"Deutschland"},{"index":951,"Unnamed: 0":951,"Jahr":1970,"Einwohner":78069000,"Bundesland":"Deutschland"},{"index":952,"Unnamed: 0":952,"Jahr":1969,"Einwohner":78269000,"Bundesland":"Deutschland"},{"index":953,"Unnamed: 0":953,"Jahr":1968,"Einwohner":77550000,"Bundesland":"Deutschland"},{"index":954,"Unnamed: 0":954,"Jahr":1967,"Einwohner":77038000,"Bundesland":"Deutschland"},{"index":955,"Unnamed: 0":955,"Jahr":1966,"Einwohner":76864000,"Bundesland":"Deutschland"},{"index":956,"Unnamed: 0":956,"Jahr":1965,"Einwohner":76336000,"Bundesland":"Deutschland"},{"index":957,"Unnamed: 0":957,"Jahr":1964,"Einwohner":75591000,"Bundesland":"Deutschland"},{"index":958,"Unnamed: 0":958,"Jahr":1963,"Einwohner":75046000,"Bundesland":"Deutschland"},{"index":959,"Unnamed: 0":959,"Jahr":1961,"Einwohner":73668000,"Bundesland":"Deutschland"},{"index":960,"Unnamed: 0":960,"Jahr":1960,"Einwohner":73147000,"Bundesland":"Deutschland"},{"index":961,"Unnamed: 0":961,"Jahr":1959,"Einwohner":72543000,"Bundesland":"Deutschland"},{"index":962,"Unnamed: 0":962,"Jahr":1958,"Einwohner":72031000,"Bundesland":"Deutschland"},{"index":963,"Unnamed: 0":963,"Jahr":1957,"Einwohner":71475000,"Bundesland":"Deutschland"},{"index":964,"Unnamed: 0":964,"Jahr":1956,"Einwohner":70943000,"Bundesland":"Deutschland"},{"index":965,"Unnamed: 0":965,"Jahr":1955,"Einwohner":71350000,"Bundesland":"Deutschland"},{"index":966,"Unnamed: 0":966,"Jahr":1954,"Einwohner":70945000,"Bundesland":"Deutschland"},{"index":967,"Unnamed: 0":967,"Jahr":1953,"Einwohner":70566000,"Bundesland":"Deutschland"},{"index":968,"Unnamed: 0":968,"Jahr":1952,"Einwohner":70164000,"Bundesland":"Deutschland"},{"index":969,"Unnamed: 0":969,"Jahr":1951,"Einwohner":69785000,"Bundesland":"Deutschland"},{"index":970,"Unnamed: 0":970,"Jahr":1950,"Einwohner":69346000,"Bundesland":"Deutschland"},{"index":971,"Unnamed: 0":971,"Jahr":1939,"Einwohner":69314000,"Bundesland":"Deutschland"},{"index":972,"Unnamed: 0":972,"Jahr":1933,"Einwohner":65218000,"Bundesland":"Deutschland"},{"index":973,"Unnamed: 0":973,"Jahr":1925,"Einwohner":62411000,"Bundesland":"Deutschland"},{"index":974,"Unnamed: 0":974,"Jahr":1910,"Einwohner":64926000,"Bundesland":"Deutschland"},{"index":975,"Unnamed: 0":975,"Jahr":1900,"Einwohner":56367000,"Bundesland":"Deutschland"},{"index":976,"Unnamed: 0":976,"Jahr":1890,"Einwohner":49428000,"Bundesland":"Deutschland"},{"index":977,"Unnamed: 0":977,"Jahr":1880,"Einwohner":45234000,"Bundesland":"Deutschland"},{"index":978,"Unnamed: 0":978,"Jahr":1871,"Einwohner":41059000,"Bundesland":"Deutschland"}]}